Workbook

Sheet Dashboard
A1: American Express Spend Report
A2: Clean summary of imported card statements.
A4: Statements | D4: Transactions | G4: Spend HKD
A5: 19 | D5: =COUNTA('Amex Transactions'!$C:$C)-1 | G5: =SUMIF('Amex Transactions'!$G:$G,">0",'Amex Transactions'!$G:$G)
A7: Payments/Credits HKD | D7: Net HKD | G7: Review Items
A8: =SUMIF('Amex Transactions'!$G:$G,"<0",'Amex Transactions'!$G:$G) | D8: =SUM('Amex Transactions'!$G:$G) | G8: =COUNTIF('Amex Transactions'!$I:$I,"Check")
A10: Date Range | B10: 25 Aug 2024 to 25 Mar 2026
A12: Top Categories | E12: Recent Statements
A13: Category | B13: Spend HKD | E13: Date | F13: Statement | G13: Rows | H13: Review
A14: Uncategorised | B14: =SUMIFS('Amex Transactions'!$G:$G,'Amex Transactions'!$D:$D,"Uncategorised",'Amex Transactions'!$G:$G,">0") | E14: 46107 | F14: 20260326 statement.pdf | G14: 84 | H14: 21
A15: Clothes & Shoes | B15: =SUMIFS('Amex Transactions'!$G:$G,'Amex Transactions'!$D:$D,"Clothes & Shoes",'Amex Transactions'!$G:$G,">0") | E15: 46079 | F15: 20260226 statement.pdf | G15: 83 | H15: 31
A16: Travel | B16: =SUMIFS('Amex Transactions'!$G:$G,'Amex Transactions'!$D:$D,"Travel",'Amex Transactions'!$G:$G,">0") | E16: 46048 | F16: 20260126 statement.pdf | G16: 40 | H16: 17
A17: Hotel | B17: =SUMIFS('Amex Transactions'!$G:$G,'Amex Transactions'!$D:$D,"Hotel",'Amex Transactions'!$G:$G,">0") | E17: 46017 | F17: 20251226 statement.pdf | G17: 101 | H17: 45
A18: Dining out | B18: =SUMIFS('Amex Transactions'!$G:$G,'Amex Transactions'!$D:$D,"Dining out",'Amex Transactions'!$G:$G,">0") | E18: 45987 | F18: 20251126 statement.pdf | G18: 125 | H18: 31
A19: Wine | B19: =SUMIFS('Amex Transactions'!$G:$G,'Amex Transactions'!$D:$D,"Wine",'Amex Transactions'!$G:$G,">0") | E19: 45956 | F19: 20251026 statement.pdf | G19: 69 | H19: 24
A20: Housewares | B20: =SUMIFS('Amex Transactions'!$G:$G,'Amex Transactions'!$D:$D,"Housewares",'Amex Transactions'!$G:$G,">0") | E20: 45926 | F20: 20250926 statement.pdf | G20: 55 | H20: 20
A21: Salon | B21: =SUMIFS('Amex Transactions'!$G:$G,'Amex Transactions'!$D:$D,"Salon",'Amex Transactions'!$G:$G,">0") | E21: 45895 | F21: 20250826 statement.pdf | G21: 81 | H21: 19
A22: Groceries | B22: =SUMIFS('Amex Transactions'!$G:$G,'Amex Transactions'!$D:$D,"Groceries",'Amex Transactions'!$G:$G,">0") | E22: 45864 | F22: 20250726 statement.pdf | G22: 43 | H22: 1
A23: Beauty | B23: =SUMIFS('Amex Transactions'!$G:$G,'Amex Transactions'!$D:$D,"Beauty",'Amex Transactions'!$G:$G,">0") | E23: 45834 | F23: 20250626 statement.pdf | G23: 83 | H23: 32
A24: Airfare | B24: =SUMIFS('Amex Transactions'!$G:$G,'Amex Transactions'!$D:$D,"Airfare",'Amex Transactions'!$G:$G,">0")
A25: Fees | B25: =SUMIFS('Amex Transactions'!$G:$G,'Amex Transactions'!$D:$D,"Fees",'Amex Transactions'!$G:$G,">0")

Sheet Monthly Summary
A1: Monthly Summary
A2: Spend and payments by month.
A4: Month | B4: Transactions | C4: Spend HKD | D4: Payments/Credits HKD | E4: Net HKD | F4: Review Items
A5: 2024-08 | B5: =COUNTIFS('Amex Transactions'!$B:$B,">="&DATEVALUE(A5&"-01"),'Amex Transactions'!$B:$B,"<"&EDATE(DATEVALUE(A5&"-01"),1)) | C5: =SUMIFS('Amex Transactions'!$G:$G,'Amex Transactions'!$B:$B,">="&DATEVALUE(A5&"-01"),'Amex Transactions'!$B:$B,"<"&EDATE(DATEVALUE(A5&"-01"),1),'Amex Transactions'!$G:$G,">0") | D5: =SUMIFS('Amex Transactions'!$G:$G,'Amex Transactions'!$B:$B,">="&DATEVALUE(A5&"-01"),'Amex Transactions'!$B:$B,"<"&EDATE(DATEVALUE(A5&"-01"),1),'Amex Transactions'!$G:$G,"<0") | E5: =C5+D5 | F5: =COUNTIFS('Amex Transactions'!$B:$B,">="&DATEVALUE(A5&"-01"),'Amex Transactions'!$B:$B,"<"&EDATE(DATEVALUE(A5&"-01"),1),'Amex Transactions'!$I:$I,"Check")
A6: 2024-09 | B6: =COUNTIFS('Amex Transactions'!$B:$B,">="&DATEVALUE(A6&"-01"),'Amex Transactions'!$B:$B,"<"&EDATE(DATEVALUE(A6&"-01"),1)) | C6: =SUMIFS('Amex Transactions'!$G:$G,'Amex Transactions'!$B:$B,">="&DATEVALUE(A6&"-01"),'Amex Transactions'!$B:$B,"<"&EDATE(DATEVALUE(A6&"-01"),1),'Amex Transactions'!$G:$G,">0") | D6: =SUMIFS('Amex Transactions'!$G:$G,'Amex Transactions'!$B:$B,">="&DATEVALUE(A6&"-01"),'Amex Transactions'!$B:$B,"<"&EDATE(DATEVALUE(A6&"-01"),1),'Amex Transactions'!$G:$G,"<0") | E6: =C6+D6 | F6: =COUNTIFS('Amex Transactions'!$B:$B,">="&DATEVALUE(A6&"-01"),'Amex Transactions'!$B:$B,"<"&EDATE(DATEVALUE(A6&"-01"),1),'Amex Transactions'!$I:$I,"Check")
A7: 2024-10 | B7: =COUNTIFS('Amex Transactions'!$B:$B,">="&DATEVALUE(A7&"-01"),'Amex Transactions'!$B:$B,"<"&EDATE(DATEVALUE(A7&"-01"),1)) | C7: =SUMIFS('Amex Transactions'!$G:$G,'Amex Transactions'!$B:$B,">="&DATEVALUE(A7&"-01"),'Amex Transactions'!$B:$B,"<"&EDATE(DATEVALUE(A7&"-01"),1),'Amex Transactions'!$G:$G,">0") | D7: =SUMIFS('Amex Transactions'!$G:$G,'Amex Transactions'!$B:$B,">="&DATEVALUE(A7&"-01"),'Amex Transactions'!$B:$B,"<"&EDATE(DATEVALUE(A7&"-01"),1),'Amex Transactions'!$G:$G,"<0") | E7: =C7+D7 | F7: =COUNTIFS('Amex Transactions'!$B:$B,">="&DATEVALUE(A7&"-01"),'Amex Transactions'!$B:$B,"<"&EDATE(DATEVALUE(A7&"-01"),1),'Amex Transactions'!$I:$I,"Check")
A8: 2024-11 | B8: =COUNTIFS('Amex Transactions'!$B:$B,">="&DATEVALUE(A8&"-01"),'Amex Transactions'!$B:$B,"<"&EDATE(DATEVALUE(A8&"-01"),1)) | C8: =SUMIFS('Amex Transactions'!$G:$G,'Amex Transactions'!$B:$B,">="&DATEVALUE(A8&"-01"),'Amex Transactions'!$B:$B,"<"&EDATE(DATEVALUE(A8&"-01"),1),'Amex Transactions'!$G:$G,">0") | D8: =SUMIFS('Amex Transactions'!$G:$G,'Amex Transactions'!$B:$B,">="&DATEVALUE(A8&"-01"),'Amex Transactions'!$B:$B,"<"&EDATE(DATEVALUE(A8&"-01"),1),'Amex Transactions'!$G:$G,"<0") | E8: =C8+D8 | F8: =COUNTIFS('Amex Transactions'!$B:$B,">="&DATEVALUE(A8&"-01"),'Amex Transactions'!$B:$B,"<"&EDATE(DATEVALUE(A8&"-01"),1),'Amex Transactions'!$I:$I,"Check")
A9: 2024-12 | B9: =COUNTIFS('Amex Transactions'!$B:$B,">="&DATEVALUE(A9&"-01"),'Amex Transactions'!$B:$B,"<"&EDATE(DATEVALUE(A9&"-01"),1)) | C9: =SUMIFS('Amex Transactions'!$G:$G,'Amex Transactions'!$B:$B,">="&DATEVALUE(A9&"-01"),'Amex Transactions'!$B:$B,"<"&EDATE(DATEVALUE(A9&"-01"),1),'Amex Transactions'!$G:$G,">0") | D9: =SUMIFS('Amex Transactions'!$G:$G,'Amex Transactions'!$B:$B,">="&DATEVALUE(A9&"-01"),'Amex Transactions'!$B:$B,"<"&EDATE(DATEVALUE(A9&"-01"),1),'Amex Transactions'!$G:$G,"<0") | E9: =C9+D9 | F9: =COUNTIFS('Amex Transactions'!$B:$B,">="&DATEVALUE(A9&"-01"),'Amex Transactions'!$B:$B,"<"&EDATE(DATEVALUE(A9&"-01"),1),'Amex Transactions'!$I:$I,"Check")
A10: 2025-01 | B10: =COUNTIFS('Amex Transactions'!$B:$B,">="&DATEVALUE(A10&"-01"),'Amex Transactions'!$B:$B,"<"&EDATE(DATEVALUE(A10&"-01"),1)) | C10: =SUMIFS('Amex Transactions'!$G:$G,'Amex Transactions'!$B:$B,">="&DATEVALUE(A10&"-01"),'Amex Transactions'!$B:$B,"<"&EDATE(DATEVALUE(A10&"-01"),1),'Amex Transactions'!$G:$G,">0") | D10: =SUMIFS('Amex Transactions'!$G:$G,'Amex Transactions'!$B:$B,">="&DATEVALUE(A10&"-01"),'Amex Transactions'!$B:$B,"<"&EDATE(DATEVALUE(A10&"-01"),1),'Amex Transactions'!$G:$G,"<0") | E10: =C10+D10 | F10: =COUNTIFS('Amex Transactions'!$B:$B,">="&DATEVALUE(A10&"-01"),'Amex Transactions'!$B:$B,"<"&EDATE(DATEVALUE(A10&"-01"),1),'Amex Transactions'!$I:$I,"Check")
A11: 2025-02 | B11: =COUNTIFS('Amex Transactions'!$B:$B,">="&DATEVALUE(A11&"-01"),'Amex Transactions'!$B:$B,"<"&EDATE(DATEVALUE(A11&"-01"),1)) | C11: =SUMIFS('Amex Transactions'!$G:$G,'Amex Transactions'!$B:$B,">="&DATEVALUE(A11&"-01"),'Amex Transactions'!$B:$B,"<"&EDATE(DATEVALUE(A11&"-01"),1),'Amex Transactions'!$G:$G,">0") | D11: =SUMIFS('Amex Transactions'!$G:$G,'Amex Transactions'!$B:$B,">="&DATEVALUE(A11&"-01"),'Amex Transactions'!$B:$B,"<"&EDATE(DATEVALUE(A11&"-01"),1),'Amex Transactions'!$G:$G,"<0") | E11: =C11+D11 | F11: =COUNTIFS('Amex Transactions'!$B:$B,">="&DATEVALUE(A11&"-01"),'Amex Transactions'!$B:$B,"<"&EDATE(DATEVALUE(A11&"-01"),1),'Amex Transactions'!$I:$I,"Check")
A12: 2025-03 | B12: =COUNTIFS('Amex Transactions'!$B:$B,">="&DATEVALUE(A12&"-01"),'Amex Transactions'!$B:$B,"<"&EDATE(DATEVALUE(A12&"-01"),1)) | C12: =SUMIFS('Amex Transactions'!$G:$G,'Amex Transactions'!$B:$B,">="&DATEVALUE(A12&"-01"),'Amex Transactions'!$B:$B,"<"&EDATE(DATEVALUE(A12&"-01"),1),'Amex Transactions'!$G:$G,">0") | D12: =SUMIFS('Amex Transactions'!$G:$G,'Amex Transactions'!$B:$B,">="&DATEVALUE(A12&"-01"),'Amex Transactions'!$B:$B,"<"&EDATE(DATEVALUE(A12&"-01"),1),'Amex Transactions'!$G:$G,"<0") | E12: =C12+D12 | F12: =COUNTIFS('Amex Transactions'!$B:$B,">="&DATEVALUE(A12&"-01"),'Amex Transactions'!$B:$B,"<"&EDATE(DATEVALUE(A12&"-01"),1),'Amex Transactions'!$I:$I,"Check")
A13: 2025-04 | B13: =COUNTIFS('Amex Transactions'!$B:$B,">="&DATEVALUE(A13&"-01"),'Amex Transactions'!$B:$B,"<"&EDATE(DATEVALUE(A13&"-01"),1)) | C13: =SUMIFS('Amex Transactions'!$G:$G,'Amex Transactions'!$B:$B,">="&DATEVALUE(A13&"-01"),'Amex Transactions'!$B:$B,"<"&EDATE(DATEVALUE(A13&"-01"),1),'Amex Transactions'!$G:$G,">0") | D13: =SUMIFS('Amex Transactions'!$G:$G,'Amex Transactions'!$B:$B,">="&DATEVALUE(A13&"-01"),'Amex Transactions'!$B:$B,"<"&EDATE(DATEVALUE(A13&"-01"),1),'Amex Transactions'!$G:$G,"<0") | E13: =C13+D13 | F13: =COUNTIFS('Amex Transactions'!$B:$B,">="&DATEVALUE(A13&"-01"),'Amex Transactions'!$B:$B,"<"&EDATE(DATEVALUE(A13&"-01"),1),'Amex Transactions'!$I:$I,"Check")
A14: 2025-05 | B14: =COUNTIFS('Amex Transactions'!$B:$B,">="&DATEVALUE(A14&"-01"),'Amex Transactions'!$B:$B,"<"&EDATE(DATEVALUE(A14&"-01"),1)) | C14: =SUMIFS('Amex Transactions'!$G:$G,'Amex Transactions'!$B:$B,">="&DATEVALUE(A14&"-01"),'Amex Transactions'!$B:$B,"<"&EDATE(DATEVALUE(A14&"-01"),1),'Amex Transactions'!$G:$G,">0") | D14: =SUMIFS('Amex Transactions'!$G:$G,'Amex Transactions'!$B:$B,">="&DATEVALUE(A14&"-01"),'Amex Transactions'!$B:$B,"<"&EDATE(DATEVALUE(A14&"-01"),1),'Amex Transactions'!$G:$G,"<0") | E14: =C14+D14 | F14: =COUNTIFS('Amex Transactions'!$B:$B,">="&DATEVALUE(A14&"-01"),'Amex Transactions'!$B:$B,"<"&EDATE(DATEVALUE(A14&"-01"),1),'Amex Transactions'!$I:$I,"Check")
A15: 2025-06 | B15: =COUNTIFS('Amex Transactions'!$B:$B,">="&DATEVALUE(A15&"-01"),'Amex Transactions'!$B:$B,"<"&EDATE(DATEVALUE(A15&"-01"),1)) | C15: =SUMIFS('Amex Transactions'!$G:$G,'Amex Transactions'!$B:$B,">="&DATEVALUE(A15&"-01"),'Amex Transactions'!$B:$B,"<"&EDATE(DATEVALUE(A15&"-01"),1),'Amex Transactions'!$G:$G,">0") | D15: =SUMIFS('Amex Transactions'!$G:$G,'Amex Transactions'!$B:$B,">="&DATEVALUE(A15&"-01"),'Amex Transactions'!$B:$B,"<"&EDATE(DATEVALUE(A15&"-01"),1),'Amex Transactions'!$G:$G,"<0") | E15: =C15+D15 | F15: =COUNTIFS('Amex Transactions'!$B:$B,">="&DATEVALUE(A15&"-01"),'Amex Transactions'!$B:$B,"<"&EDATE(DATEVALUE(A15&"-01"),1),'Amex Transactions'!$I:$I,"Check")
A16: 2025-07 | B16: =COUNTIFS('Amex Transactions'!$B:$B,">="&DATEVALUE(A16&"-01"),'Amex Transactions'!$B:$B,"<"&EDATE(DATEVALUE(A16&"-01"),1)) | C16: =SUMIFS('Amex Transactions'!$G:$G,'Amex Transactions'!$B:$B,">="&DATEVALUE(A16&"-01"),'Amex Transactions'!$B:$B,"<"&EDATE(DATEVALUE(A16&"-01"),1),'Amex Transactions'!$G:$G,">0") | D16: =SUMIFS('Amex Transactions'!$G:$G,'Amex Transactions'!$B:$B,">="&DATEVALUE(A16&"-01"),'Amex Transactions'!$B:$B,"<"&EDATE(DATEVALUE(A16&"-01"),1),'Amex Transactions'!$G:$G,"<0") | E16: =C16+D16 | F16: =COUNTIFS('Amex Transactions'!$B:$B,">="&DATEVALUE(A16&"-01"),'Amex Transactions'!$B:$B,"<"&EDATE(DATEVALUE(A16&"-01"),1),'Amex Transactions'!$I:$I,"Check")
... A24: 2026-03 | B24: =COUNTIFS('Amex Transactions'!$B:$B,">="&DATEVALUE(A24&"-01"),'Amex Transactions'!$B:$B,"<"&EDATE(DATEVALUE(A24&"-01"),1)) | C24: =SUMIFS('Amex Transactions'!$G:$G,'Amex Transactions'!$B:$B,">="&DATEVALUE(A24&"-01"),'Amex Transactions'!$B:$B,"<"&EDATE(DATEVALUE(A24&"-01"),1),'Amex Transactions'!$G:$G,">0") | D24: =SUMIFS('Amex Transactions'!$G:$G,'Amex Transactions'!$B:$B,">="&DATEVALUE(A24&"-01"),'Amex Transactions'!$B:$B,"<"&EDATE(DATEVALUE(A24&"-01"),1),'Amex Transactions'!$G:$G,"<0") | E24: =C24+D24 | F24: =COUNTIFS('Amex Transactions'!$B:$B,">="&DATEVALUE(A24&"-01"),'Amex Transactions'!$B:$B,"<"&EDATE(DATEVALUE(A24&"-01"),1),'Amex Transactions'!$I:$I,"Check")

Sheet Category Summary
A1: Category Summary
A2: Spend by owner and category.
A4: Belongs To | B4: Category | C4: Transactions | D4: Spend HKD | E4: Payments/Credits HKD | F4: Net HKD | G4: Review Items
A5: Family | B5: Airfare | C5: =COUNTIFS('Amex Transactions'!$E:$E,A5,'Amex Transactions'!$D:$D,B5) | D5: =SUMIFS('Amex Transactions'!$G:$G,'Amex Transactions'!$E:$E,A5,'Amex Transactions'!$D:$D,B5,'Amex Transactions'!$G:$G,">0") | E5: =SUMIFS('Amex Transactions'!$G:$G,'Amex Transactions'!$E:$E,A5,'Amex Transactions'!$D:$D,B5,'Amex Transactions'!$G:$G,"<0") | F5: =D5+E5 | G5: =COUNTIFS('Amex Transactions'!$E:$E,A5,'Amex Transactions'!$D:$D,B5,'Amex Transactions'!$I:$I,"Check")
A6: Family | B6: Art | C6: =COUNTIFS('Amex Transactions'!$E:$E,A6,'Amex Transactions'!$D:$D,B6) | D6: =SUMIFS('Amex Transactions'!$G:$G,'Amex Transactions'!$E:$E,A6,'Amex Transactions'!$D:$D,B6,'Amex Transactions'!$G:$G,">0") | E6: =SUMIFS('Amex Transactions'!$G:$G,'Amex Transactions'!$E:$E,A6,'Amex Transactions'!$D:$D,B6,'Amex Transactions'!$G:$G,"<0") | F6: =D6+E6 | G6: =COUNTIFS('Amex Transactions'!$E:$E,A6,'Amex Transactions'!$D:$D,B6,'Amex Transactions'!$I:$I,"Check")
A7: Family | B7: Beauty | C7: =COUNTIFS('Amex Transactions'!$E:$E,A7,'Amex Transactions'!$D:$D,B7) | D7: =SUMIFS('Amex Transactions'!$G:$G,'Amex Transactions'!$E:$E,A7,'Amex Transactions'!$D:$D,B7,'Amex Transactions'!$G:$G,">0") | E7: =SUMIFS('Amex Transactions'!$G:$G,'Amex Transactions'!$E:$E,A7,'Amex Transactions'!$D:$D,B7,'Amex Transactions'!$G:$G,"<0") | F7: =D7+E7 | G7: =COUNTIFS('Amex Transactions'!$E:$E,A7,'Amex Transactions'!$D:$D,B7,'Amex Transactions'!$I:$I,"Check")
A8: Family | B8: Book & Kindle | C8: =COUNTIFS('Amex Transactions'!$E:$E,A8,'Amex Transactions'!$D:$D,B8) | D8: =SUMIFS('Amex Transactions'!$G:$G,'Amex Transactions'!$E:$E,A8,'Amex Transactions'!$D:$D,B8,'Amex Transactions'!$G:$G,">0") | E8: =SUMIFS('Amex Transactions'!$G:$G,'Amex Transactions'!$E:$E,A8,'Amex Transactions'!$D:$D,B8,'Amex Transactions'!$G:$G,"<0") | F8: =D8+E8 | G8: =COUNTIFS('Amex Transactions'!$E:$E,A8,'Amex Transactions'!$D:$D,B8,'Amex Transactions'!$I:$I,"Check")
A9: Family | B9: Charity | C9: =COUNTIFS('Amex Transactions'!$E:$E,A9,'Amex Transactions'!$D:$D,B9) | D9: =SUMIFS('Amex Transactions'!$G:$G,'Amex Transactions'!$E:$E,A9,'Amex Transactions'!$D:$D,B9,'Amex Transactions'!$G:$G,">0") | E9: =SUMIFS('Amex Transactions'!$G:$G,'Amex Transactions'!$E:$E,A9,'Amex Transactions'!$D:$D,B9,'Amex Transactions'!$G:$G,"<0") | F9: =D9+E9 | G9: =COUNTIFS('Amex Transactions'!$E:$E,A9,'Amex Transactions'!$D:$D,B9,'Amex Transactions'!$I:$I,"Check")
A10: Family | B10: Clinic | C10: =COUNTIFS('Amex Transactions'!$E:$E,A10,'Amex Transactions'!$D:$D,B10) | D10: =SUMIFS('Amex Transactions'!$G:$G,'Amex Transactions'!$E:$E,A10,'Amex Transactions'!$D:$D,B10,'Amex Transactions'!$G:$G,">0") | E10: =SUMIFS('Amex Transactions'!$G:$G,'Amex Transactions'!$E:$E,A10,'Amex Transactions'!$D:$D,B10,'Amex Transactions'!$G:$G,"<0") | F10: =D10+E10 | G10: =COUNTIFS('Amex Transactions'!$E:$E,A10,'Amex Transactions'!$D:$D,B10,'Amex Transactions'!$I:$I,"Check")
A11: Family | B11: Clothes & Shoes | C11: =COUNTIFS('Amex Transactions'!$E:$E,A11,'Amex Transactions'!$D:$D,B11) | D11: =SUMIFS('Amex Transactions'!$G:$G,'Amex Transactions'!$E:$E,A11,'Amex Transactions'!$D:$D,B11,'Amex Transactions'!$G:$G,">0") | E11: =SUMIFS('Amex Transactions'!$G:$G,'Amex Transactions'!$E:$E,A11,'Amex Transactions'!$D:$D,B11,'Amex Transactions'!$G:$G,"<0") | F11: =D11+E11 | G11: =COUNTIFS('Amex Transactions'!$E:$E,A11,'Amex Transactions'!$D:$D,B11,'Amex Transactions'!$I:$I,"Check")
A12: Family | B12: Dining out | C12: =COUNTIFS('Amex Transactions'!$E:$E,A12,'Amex Transactions'!$D:$D,B12) | D12: =SUMIFS('Amex Transactions'!$G:$G,'Amex Transactions'!$E:$E,A12,'Amex Transactions'!$D:$D,B12,'Amex Transactions'!$G:$G,">0") | E12: =SUMIFS('Amex Transactions'!$G:$G,'Amex Transactions'!$E:$E,A12,'Amex Transactions'!$D:$D,B12,'Amex Transactions'!$G:$G,"<0") | F12: =D12+E12 | G12: =COUNTIFS('Amex Transactions'!$E:$E,A12,'Amex Transactions'!$D:$D,B12,'Amex Transactions'!$I:$I,"Check")
A13: Family | B13: Electronics | C13: =COUNTIFS('Amex Transactions'!$E:$E,A13,'Amex Transactions'!$D:$D,B13) | D13: =SUMIFS('Amex Transactions'!$G:$G,'Amex Transactions'!$E:$E,A13,'Amex Transactions'!$D:$D,B13,'Amex Transactions'!$G:$G,">0") | E13: =SUMIFS('Amex Transactions'!$G:$G,'Amex Transactions'!$E:$E,A13,'Amex Transactions'!$D:$D,B13,'Amex Transactions'!$G:$G,"<0") | F13: =D13+E13 | G13: =COUNTIFS('Amex Transactions'!$E:$E,A13,'Amex Transactions'!$D:$D,B13,'Amex Transactions'!$I:$I,"Check")
A14: Family | B14: Entertainment | C14: =COUNTIFS('Amex Transactions'!$E:$E,A14,'Amex Transactions'!$D:$D,B14) | D14: =SUMIFS('Amex Transactions'!$G:$G,'Amex Transactions'!$E:$E,A14,'Amex Transactions'!$D:$D,B14,'Amex Transactions'!$G:$G,">0") | E14: =SUMIFS('Amex Transactions'!$G:$G,'Amex Transactions'!$E:$E,A14,'Amex Transactions'!$D:$D,B14,'Amex Transactions'!$G:$G,"<0") | F14: =D14+E14 | G14: =COUNTIFS('Amex Transactions'!$E:$E,A14,'Amex Transactions'!$D:$D,B14,'Amex Transactions'!$I:$I,"Check")
A15: Family | B15: Fees | C15: =COUNTIFS('Amex Transactions'!$E:$E,A15,'Amex Transactions'!$D:$D,B15) | D15: =SUMIFS('Amex Transactions'!$G:$G,'Amex Transactions'!$E:$E,A15,'Amex Transactions'!$D:$D,B15,'Amex Transactions'!$G:$G,">0") | E15: =SUMIFS('Amex Transactions'!$G:$G,'Amex Transactions'!$E:$E,A15,'Amex Transactions'!$D:$D,B15,'Amex Transactions'!$G:$G,"<0") | F15: =D15+E15 | G15: =COUNTIFS('Amex Transactions'!$E:$E,A15,'Amex Transactions'!$D:$D,B15,'Amex Transactions'!$I:$I,"Check")
A16: Family | B16: Fitness Equipment | C16: =COUNTIFS('Amex Transactions'!$E:$E,A16,'Amex Transactions'!$D:$D,B16) | D16: =SUMIFS('Amex Transactions'!$G:$G,'Amex Transactions'!$E:$E,A16,'Amex Transactions'!$D:$D,B16,'Amex Transactions'!$G:$G,">0") | E16: =SUMIFS('Amex Transactions'!$G:$G,'Amex Transactions'!$E:$E,A16,'Amex Transactions'!$D:$D,B16,'Amex Transactions'!$G:$G,"<0") | F16: =D16+E16 | G16: =COUNTIFS('Amex Transactions'!$E:$E,A16,'Amex Transactions'!$D:$D,B16,'Amex Transactions'!$I:$I,"Check")
... A110: Su | B110: beauty | C110: =COUNTIFS('Amex Transactions'!$E:$E,A110,'Amex Transactions'!$D:$D,B110) | D110: =SUMIFS('Amex Transactions'!$G:$G,'Amex Transactions'!$E:$E,A110,'Amex Transactions'!$D:$D,B110,'Amex Transactions'!$G:$G,">0") | E110: =SUMIFS('Amex Transactions'!$G:$G,'Amex Transactions'!$E:$E,A110,'Amex Transactions'!$D:$D,B110,'Amex Transactions'!$G:$G,"<0") | F110: =D110+E110 | G110: =COUNTIFS('Amex Transactions'!$E:$E,A110,'Amex Transactions'!$D:$D,B110,'Amex Transactions'!$I:$I,"Check")

Sheet Merchant Summary
A1: Merchant Summary
A2: Largest merchants across all statements.
A4: Merchant | B4: Category | C4: Belongs To | D4: Transactions | E4: Spend HKD | F4: Last Date | G4: Review
A5: SILVERSEA LONDON | B5: =IFERROR(INDEX('Review Items'!$D:$D,MATCH(A5,'Review Items'!$B:$B,0)),IFERROR(INDEX('Rule Updates'!$B:$B,MATCH(A5,'Rule Updates'!$A:$A,0)),"Uncategorised")) | C5: =IFERROR(INDEX('Review Items'!$E:$E,MATCH(A5,'Review Items'!$B:$B,0)),IFERROR(INDEX('Rule Updates'!$C:$C,MATCH(A5,'Rule Updates'!$A:$A,0)),"Review")) | D5: =COUNTIF('Amex Transactions'!$C:$C,A5) | E5: =SUMIFS('Amex Transactions'!$G:$G,'Amex Transactions'!$C:$C,A5,'Amex Transactions'!$G:$G,">0") | F5: 45562 | G5: =IF(COUNTIFS('Amex Transactions'!$C:$C,A5,'Amex Transactions'!$I:$I,"Check")>0,"Check","")
A6: THE NET-A-PORTER GROUP HONG KONG | B6: =IFERROR(INDEX('Review Items'!$D:$D,MATCH(A6,'Review Items'!$B:$B,0)),IFERROR(INDEX('Rule Updates'!$B:$B,MATCH(A6,'Rule Updates'!$A:$A,0)),"Uncategorised")) | C6: =IFERROR(INDEX('Review Items'!$E:$E,MATCH(A6,'Review Items'!$B:$B,0)),IFERROR(INDEX('Rule Updates'!$C:$C,MATCH(A6,'Rule Updates'!$A:$A,0)),"Review")) | D6: =COUNTIF('Amex Transactions'!$C:$C,A6) | E6: =SUMIFS('Amex Transactions'!$G:$G,'Amex Transactions'!$C:$C,A6,'Amex Transactions'!$G:$G,">0") | F6: 46106 | G6: =IF(COUNTIFS('Amex Transactions'!$C:$C,A6,'Amex Transactions'!$I:$I,"Check")>0,"Check","")
A7: MYTHERESA APAC SERVICES ISLANDS | B7: =IFERROR(INDEX('Review Items'!$D:$D,MATCH(A7,'Review Items'!$B:$B,0)),IFERROR(INDEX('Rule Updates'!$B:$B,MATCH(A7,'Rule Updates'!$A:$A,0)),"Uncategorised")) | C7: =IFERROR(INDEX('Review Items'!$E:$E,MATCH(A7,'Review Items'!$B:$B,0)),IFERROR(INDEX('Rule Updates'!$C:$C,MATCH(A7,'Rule Updates'!$A:$A,0)),"Review")) | D7: =COUNTIF('Amex Transactions'!$C:$C,A7) | E7: =SUMIFS('Amex Transactions'!$G:$G,'Amex Transactions'!$C:$C,A7,'Amex Transactions'!$G:$G,">0") | F7: 46106 | G7: =IF(COUNTIFS('Amex Transactions'!$C:$C,A7,'Amex Transactions'!$I:$I,"Check")>0,"Check","")
A8: HTL*ASCOTTORCHARDS 800-468-3578 | B8: =IFERROR(INDEX('Review Items'!$D:$D,MATCH(A8,'Review Items'!$B:$B,0)),IFERROR(INDEX('Rule Updates'!$B:$B,MATCH(A8,'Rule Updates'!$A:$A,0)),"Uncategorised")) | C8: =IFERROR(INDEX('Review Items'!$E:$E,MATCH(A8,'Review Items'!$B:$B,0)),IFERROR(INDEX('Rule Updates'!$C:$C,MATCH(A8,'Rule Updates'!$A:$A,0)),"Review")) | D8: =COUNTIF('Amex Transactions'!$C:$C,A8) | E8: =SUMIFS('Amex Transactions'!$G:$G,'Amex Transactions'!$C:$C,A8,'Amex Transactions'!$G:$G,">0") | F8: 45572 | G8: =IF(COUNTIFS('Amex Transactions'!$C:$C,A8,'Amex Transactions'!$I:$I,"Check")>0,"Check","")
A9: WHALE CLU BHK | B9: =IFERROR(INDEX('Review Items'!$D:$D,MATCH(A9,'Review Items'!$B:$B,0)),IFERROR(INDEX('Rule Updates'!$B:$B,MATCH(A9,'Rule Updates'!$A:$A,0)),"Uncategorised")) | C9: =IFERROR(INDEX('Review Items'!$E:$E,MATCH(A9,'Review Items'!$B:$B,0)),IFERROR(INDEX('Rule Updates'!$C:$C,MATCH(A9,'Rule Updates'!$A:$A,0)),"Review")) | D9: =COUNTIF('Amex Transactions'!$C:$C,A9) | E9: =SUMIFS('Amex Transactions'!$G:$G,'Amex Transactions'!$C:$C,A9,'Amex Transactions'!$G:$G,">0") | F9: 46036 | G9: =IF(COUNTIFS('Amex Transactions'!$C:$C,A9,'Amex Transactions'!$I:$I,"Check")>0,"Check","")
A10: PONTI WINE CELLARS 0000 HONG KONG | B10: =IFERROR(INDEX('Review Items'!$D:$D,MATCH(A10,'Review Items'!$B:$B,0)),IFERROR(INDEX('Rule Updates'!$B:$B,MATCH(A10,'Rule Updates'!$A:$A,0)),"Uncategorised")) | C10: =IFERROR(INDEX('Review Items'!$E:$E,MATCH(A10,'Review Items'!$B:$B,0)),IFERROR(INDEX('Rule Updates'!$C:$C,MATCH(A10,'Rule Updates'!$A:$A,0)),"Review")) | D10: =COUNTIF('Amex Transactions'!$C:$C,A10) | E10: =SUMIFS('Amex Transactions'!$G:$G,'Amex Transactions'!$C:$C,A10,'Amex Transactions'!$G:$G,">0") | F10: 46097 | G10: =IF(COUNTIFS('Amex Transactions'!$C:$C,A10,'Amex Transactions'!$I:$I,"Check")>0,"Check","")
A11: LANE CRAWFORD (FURNITUR ADMIRALTY | B11: =IFERROR(INDEX('Review Items'!$D:$D,MATCH(A11,'Review Items'!$B:$B,0)),IFERROR(INDEX('Rule Updates'!$B:$B,MATCH(A11,'Rule Updates'!$A:$A,0)),"Uncategorised")) | C11: =IFERROR(INDEX('Review Items'!$E:$E,MATCH(A11,'Review Items'!$B:$B,0)),IFERROR(INDEX('Rule Updates'!$C:$C,MATCH(A11,'Rule Updates'!$A:$A,0)),"Review")) | D11: =COUNTIF('Amex Transactions'!$C:$C,A11) | E11: =SUMIFS('Amex Transactions'!$G:$G,'Amex Transactions'!$C:$C,A11,'Amex Transactions'!$G:$G,">0") | F11: 45799 | G11: =IF(COUNTIFS('Amex Transactions'!$C:$C,A11,'Amex Transactions'!$I:$I,"Check")>0,"Check","")
A12: RAFFLES HOTEL SINGAPORE SINGAPORE | B12: =IFERROR(INDEX('Review Items'!$D:$D,MATCH(A12,'Review Items'!$B:$B,0)),IFERROR(INDEX('Rule Updates'!$B:$B,MATCH(A12,'Rule Updates'!$A:$A,0)),"Uncategorised")) | C12: =IFERROR(INDEX('Review Items'!$E:$E,MATCH(A12,'Review Items'!$B:$B,0)),IFERROR(INDEX('Rule Updates'!$C:$C,MATCH(A12,'Rule Updates'!$A:$A,0)),"Review")) | D12: =COUNTIF('Amex Transactions'!$C:$C,A12) | E12: =SUMIFS('Amex Transactions'!$G:$G,'Amex Transactions'!$C:$C,A12,'Amex Transactions'!$G:$G,">0") | F12: 46074 | G12: =IF(COUNTIFS('Amex Transactions'!$C:$C,A12,'Amex Transactions'!$I:$I,"Check")>0,"Check","")
A13: AGORA IBIZA 367352630 SANT JOAN LAB | B13: =IFERROR(INDEX('Review Items'!$D:$D,MATCH(A13,'Review Items'!$B:$B,0)),IFERROR(INDEX('Rule Updates'!$B:$B,MATCH(A13,'Rule Updates'!$A:$A,0)),"Uncategorised")) | C13: =IFERROR(INDEX('Review Items'!$E:$E,MATCH(A13,'Review Items'!$B:$B,0)),IFERROR(INDEX('Rule Updates'!$C:$C,MATCH(A13,'Rule Updates'!$A:$A,0)),"Review")) | D13: =COUNTIF('Amex Transactions'!$C:$C,A13) | E13: =SUMIFS('Amex Transactions'!$G:$G,'Amex Transactions'!$C:$C,A13,'Amex Transactions'!$G:$G,">0") | F13: 45835 | G13: =IF(COUNTIFS('Amex Transactions'!$C:$C,A13,'Amex Transactions'!$I:$I,"Check")>0,"Check","")
A14: FAR FETCH LONDON | B14: =IFERROR(INDEX('Review Items'!$D:$D,MATCH(A14,'Review Items'!$B:$B,0)),IFERROR(INDEX('Rule Updates'!$B:$B,MATCH(A14,'Rule Updates'!$A:$A,0)),"Uncategorised")) | C14: =IFERROR(INDEX('Review Items'!$E:$E,MATCH(A14,'Review Items'!$B:$B,0)),IFERROR(INDEX('Rule Updates'!$C:$C,MATCH(A14,'Rule Updates'!$A:$A,0)),"Review")) | D14: =COUNTIF('Amex Transactions'!$C:$C,A14) | E14: =SUMIFS('Amex Transactions'!$G:$G,'Amex Transactions'!$C:$C,A14,'Amex Transactions'!$G:$G,">0") | F14: 46095 | G14: =IF(COUNTIFS('Amex Transactions'!$C:$C,A14,'Amex Transactions'!$I:$I,"Check")>0,"Check","")
A15: BURGUNDY ETC CENTRAL | B15: =IFERROR(INDEX('Review Items'!$D:$D,MATCH(A15,'Review Items'!$B:$B,0)),IFERROR(INDEX('Rule Updates'!$B:$B,MATCH(A15,'Rule Updates'!$A:$A,0)),"Uncategorised")) | C15: =IFERROR(INDEX('Review Items'!$E:$E,MATCH(A15,'Review Items'!$B:$B,0)),IFERROR(INDEX('Rule Updates'!$C:$C,MATCH(A15,'Rule Updates'!$A:$A,0)),"Review")) | D15: =COUNTIF('Amex Transactions'!$C:$C,A15) | E15: =SUMIFS('Amex Transactions'!$G:$G,'Amex Transactions'!$C:$C,A15,'Amex Transactions'!$G:$G,">0") | F15: 46003 | G15: =IF(COUNTIFS('Amex Transactions'!$C:$C,A15,'Amex Transactions'!$I:$I,"Check")>0,"Check","")
A16: 3CPAYMENT*SIX SENSES IB GETARIA | B16: =IFERROR(INDEX('Review Items'!$D:$D,MATCH(A16,'Review Items'!$B:$B,0)),IFERROR(INDEX('Rule Updates'!$B:$B,MATCH(A16,'Rule Updates'!$A:$A,0)),"Uncategorised")) | C16: =IFERROR(INDEX('Review Items'!$E:$E,MATCH(A16,'Review Items'!$B:$B,0)),IFERROR(INDEX('Rule Updates'!$C:$C,MATCH(A16,'Rule Updates'!$A:$A,0)),"Review")) | D16: =COUNTIF('Amex Transactions'!$C:$C,A16) | E16: =SUMIFS('Amex Transactions'!$G:$G,'Amex Transactions'!$C:$C,A16,'Amex Transactions'!$G:$G,">0") | F16: 45827 | G16: =IF(COUNTIFS('Amex Transactions'!$C:$C,A16,'Amex Transactions'!$I:$I,"Check")>0,"Check","")
... A692: TUMI ASIA LIMITED | B692: =IFERROR(INDEX('Review Items'!$D:$D,MATCH(A692,'Review Items'!$B:$B,0)),IFERROR(INDEX('Rule Updates'!$B:$B,MATCH(A692,'Rule Updates'!$A:$A,0)),"Uncategorised")) | C692: =IFERROR(INDEX('Review Items'!$E:$E,MATCH(A692,'Review Items'!$B:$B,0)),IFERROR(INDEX('Rule Updates'!$C:$C,MATCH(A692,'Rule Updates'!$A:$A,0)),"Review")) | D692: =COUNTIF('Amex Transactions'!$C:$C,A692) | E692: =SUMIFS('Amex Transactions'!$G:$G,'Amex Transactions'!$C:$C,A692,'Amex Transactions'!$G:$G,">0") | F692: 46076 | G692: =IF(COUNTIFS('Amex Transactions'!$C:$C,A692,'Amex Transactions'!$I:$I,"Check")>0,"Check","")

Sheet Review Items
A1: Review Items
A2: Live queue of transactions that started without a complete category/owner.
A4: Date | B4: Merchant | C4: Amount HKD | D4: Current Category | E4: Belongs To | F4: Statement | G4: Status
A5: 45529 | B5: AZABUDAIHILLS TOKYO | C5: 3640.51 | D5: Uncategorised | E5: Review | F5: Amex Sep-2024 | G5: =IF(OR(D5="Uncategorised",E5="",E5="Review"),"Needs category/owner","Resolved")
A6: 45536 | B6: LOOKOPTIC LOS ANGELES | C6: 1006.49 | D6: Uncategorised | E6: Review | F6: Amex Sep-2024 | G6: =IF(OR(D6="Uncategorised",E6="",E6="Review"),"Needs category/owner","Resolved")
A7: 45536 | B7: LOOKOPTIC LOS ANGELES | C7: 444.43 | D7: Uncategorised | E7: Review | F7: Amex Sep-2024 | G7: =IF(OR(D7="Uncategorised",E7="",E7="Review"),"Needs category/owner","Resolved")
A8: 45546 | B8: KPAY*MOMOGAWANOU 000000 HONG KONG | C8: 3340 | D8: Uncategorised | E8: Review | F8: Amex Sep-2024 | G8: =IF(OR(D8="Uncategorised",E8="",E8="Review"),"Needs category/owner","Resolved")
A9: 45562 | B9: SOGO HONG KONG CO LTD CAUSEWAY BAY | C9: 120 | D9: Uncategorised | E9: Review | F9: Amex Oct-2024 | G9: =IF(OR(D9="Uncategorised",E9="",E9="Review"),"Needs category/owner","Resolved")
A10: 45575 | B10: WWW.HYUNDAI.COM SINGAPORE | C10: 4742.32 | D10: Uncategorised | E10: Review | F10: Amex Oct-2024 | G10: =IF(OR(D10="Uncategorised",E10="",E10="Review"),"Needs category/owner","Resolved")
A11: 45576 | B11: Alice Pizza CTRL HK | C11: 261.1 | D11: Uncategorised | E11: Review | F11: Amex Oct-2024 | G11: =IF(OR(D11="Uncategorised",E11="",E11="Review"),"Needs category/owner","Resolved")
A12: 45588 | B12: WIX SQUARED LTD ST. MARTIN | C12: 32248.15 | D12: Uncategorised | E12: Review | F12: Amex Oct-2024 | G12: =IF(OR(D12="Uncategorised",E12="",E12="Review"),"Needs category/owner","Resolved")
A13: 45589 | B13: PARAGON CENTRAL | C13: 242 | D13: Uncategorised | E13: Review | F13: Amex Oct-2024 | G13: =IF(OR(D13="Uncategorised",E13="",E13="Review"),"Needs category/owner","Resolved")
A14: 45590 | B14: FIATA CENTRAL | C14: 627 | D14: Uncategorised | E14: Review | F14: Amex Oct-2024 | G14: =IF(OR(D14="Uncategorised",E14="",E14="Review"),"Needs category/owner","Resolved")
A15: 45622 | B15: CITEES CARTAGENACARMEN MURCIA | C15: 626.84 | D15: Uncategorised | E15: Review | F15: Amex Dec-2024 | G15: =IF(OR(D15="Uncategorised",E15="",E15="Review"),"Needs category/owner","Resolved")
A16: 45623 | B16: FARMACIA EL SAGRARIO 01 MALAGA | C16: 443.14 | D16: Uncategorised | E16: Review | F16: Amex Dec-2024 | G16: =IF(OR(D16="Uncategorised",E16="",E16="Review"),"Needs category/owner","Resolved")
... A386: 46104 | B386: KPAY * MAISON KARYA 00000 HONG KONG | C386: 1204.2 | D386: Uncategorised | E386: Review | F386: Amex Mar-2026 | G386: =IF(OR(D386="Uncategorised",E386="",E386="Review"),"Needs category/owner","Resolved")

Sheet Amex Transactions
A1: Amex Transactions
A2: Full transaction ledger.
A4: Statement | B4: Date | C4: Merchant | D4: Category | E4: Belongs To | F4: Foreign Spend | G4: Amount HKD | H4: Source Page | I4: Review
A5: Amex Sep-2024 | B5: 45529 | C5: AZABUDAIHILLS TOKYO | D5: =IFERROR(INDEX('Review Items'!$D:$D,MATCH(C5,'Review Items'!$B:$B,0)),IFERROR(INDEX('Rule Updates'!$B:$B,MATCH(C5,'Rule Updates'!$A:$A,0)),"Uncategorised")) | E5: =IFERROR(INDEX('Review Items'!$E:$E,MATCH(C5,'Review Items'!$B:$B,0)),IFERROR(INDEX('Rule Updates'!$C:$C,MATCH(C5,'Rule Updates'!$A:$A,0)),"Review")) | F5: 66340 | G5: 3640.51 | H5: 6 | I5: =IF(OR(D5="Uncategorised",E5=""),"Check","")
A6: Amex Sep-2024 | B6: 45531 | C6: AMATHUS (Bath) Bath | D6: =IFERROR(INDEX('Review Items'!$D:$D,MATCH(C6,'Review Items'!$B:$B,0)),IFERROR(INDEX('Rule Updates'!$B:$B,MATCH(C6,'Rule Updates'!$A:$A,0)),"Uncategorised")) | E6: =IFERROR(INDEX('Review Items'!$E:$E,MATCH(C6,'Review Items'!$B:$B,0)),IFERROR(INDEX('Rule Updates'!$C:$C,MATCH(C6,'Rule Updates'!$A:$A,0)),"Review")) | F6: 64.7 | G6: 679.91 | H6: 1 | I6: =IF(OR(D6="Uncategorised",E6=""),"Check","")
A7: Amex Sep-2024 | B7: 45531 | C7: Mr B's Emporium Bath | D7: =IFERROR(INDEX('Review Items'!$D:$D,MATCH(C7,'Review Items'!$B:$B,0)),IFERROR(INDEX('Rule Updates'!$B:$B,MATCH(C7,'Rule Updates'!$A:$A,0)),"Uncategorised")) | E7: =IFERROR(INDEX('Review Items'!$E:$E,MATCH(C7,'Review Items'!$B:$B,0)),IFERROR(INDEX('Rule Updates'!$C:$C,MATCH(C7,'Rule Updates'!$A:$A,0)),"Review")) | F7: 49.98 | G7: 525.22 | H7: 1 | I7: =IF(OR(D7="Uncategorised",E7=""),"Check","")
A8: Amex Sep-2024 | B8: 45531 | C8: TOPPING & COMPANY BOOKS Bathwick | D8: =IFERROR(INDEX('Review Items'!$D:$D,MATCH(C8,'Review Items'!$B:$B,0)),IFERROR(INDEX('Rule Updates'!$B:$B,MATCH(C8,'Rule Updates'!$A:$A,0)),"Uncategorised")) | E8: =IFERROR(INDEX('Review Items'!$E:$E,MATCH(C8,'Review Items'!$B:$B,0)),IFERROR(INDEX('Rule Updates'!$C:$C,MATCH(C8,'Rule Updates'!$A:$A,0)),"Review")) | F8: 26 | G8: 273.18 | H8: 1 | I8: =IF(OR(D8="Uncategorised",E8=""),"Check","")
A9: Amex Sep-2024 | B9: 45531 | C9: TOPPING & COMPANY BOOKS Bathwick | D9: =IFERROR(INDEX('Review Items'!$D:$D,MATCH(C9,'Review Items'!$B:$B,0)),IFERROR(INDEX('Rule Updates'!$B:$B,MATCH(C9,'Rule Updates'!$A:$A,0)),"Uncategorised")) | E9: =IFERROR(INDEX('Review Items'!$E:$E,MATCH(C9,'Review Items'!$B:$B,0)),IFERROR(INDEX('Rule Updates'!$C:$C,MATCH(C9,'Rule Updates'!$A:$A,0)),"Review")) | F9: 53.98 | G9: 567.22 | H9: 1 | I9: =IF(OR(D9="Uncategorised",E9=""),"Check","")
A10: Amex Sep-2024 | B10: 45531 | C10: WH SMITH TRAVEL RETAIL HOUNSLOW | D10: =IFERROR(INDEX('Review Items'!$D:$D,MATCH(C10,'Review Items'!$B:$B,0)),IFERROR(INDEX('Rule Updates'!$B:$B,MATCH(C10,'Rule Updates'!$A:$A,0)),"Uncategorised")) | E10: =IFERROR(INDEX('Review Items'!$E:$E,MATCH(C10,'Review Items'!$B:$B,0)),IFERROR(INDEX('Rule Updates'!$C:$C,MATCH(C10,'Rule Updates'!$A:$A,0)),"Review")) | F10: 15.74 | G10: 165.42 | H10: 1 | I10: =IF(OR(D10="Uncategorised",E10=""),"Check","")
A11: Amex Sep-2024 | B11: 45534 | C11: CLARINS LIMITED CENTRAL | D11: =IFERROR(INDEX('Review Items'!$D:$D,MATCH(C11,'Review Items'!$B:$B,0)),IFERROR(INDEX('Rule Updates'!$B:$B,MATCH(C11,'Rule Updates'!$A:$A,0)),"Uncategorised")) | E11: =IFERROR(INDEX('Review Items'!$E:$E,MATCH(C11,'Review Items'!$B:$B,0)),IFERROR(INDEX('Rule Updates'!$C:$C,MATCH(C11,'Rule Updates'!$A:$A,0)),"Review")) | G11: 3541 | H11: 2 | I11: =IF(OR(D11="Uncategorised",E11=""),"Check","")
A12: Amex Sep-2024 | B12: 45534 | C12: IL COLPO PACIFIC PLACE ADMIRALTY | D12: =IFERROR(INDEX('Review Items'!$D:$D,MATCH(C12,'Review Items'!$B:$B,0)),IFERROR(INDEX('Rule Updates'!$B:$B,MATCH(C12,'Rule Updates'!$A:$A,0)),"Uncategorised")) | E12: =IFERROR(INDEX('Review Items'!$E:$E,MATCH(C12,'Review Items'!$B:$B,0)),IFERROR(INDEX('Rule Updates'!$C:$C,MATCH(C12,'Rule Updates'!$A:$A,0)),"Review")) | G12: 4680 | H12: 2 | I12: =IF(OR(D12="Uncategorised",E12=""),"Check","")
A13: Amex Sep-2024 | B13: 45535 | C13: CITYSUPER STORE @ SOUTH WONG CHUK HANG | D13: =IFERROR(INDEX('Review Items'!$D:$D,MATCH(C13,'Review Items'!$B:$B,0)),IFERROR(INDEX('Rule Updates'!$B:$B,MATCH(C13,'Rule Updates'!$A:$A,0)),"Uncategorised")) | E13: =IFERROR(INDEX('Review Items'!$E:$E,MATCH(C13,'Review Items'!$B:$B,0)),IFERROR(INDEX('Rule Updates'!$C:$C,MATCH(C13,'Rule Updates'!$A:$A,0)),"Review")) | G13: 1728.9 | H13: 2 | I13: =IF(OR(D13="Uncategorised",E13=""),"Check","")
A14: Amex Sep-2024 | B14: 45536 | C14: AMAZON PRIME*RK2502SU0 AMZN.COM/BILL | D14: =IFERROR(INDEX('Review Items'!$D:$D,MATCH(C14,'Review Items'!$B:$B,0)),IFERROR(INDEX('Rule Updates'!$B:$B,MATCH(C14,'Rule Updates'!$A:$A,0)),"Uncategorised")) | E14: =IFERROR(INDEX('Review Items'!$E:$E,MATCH(C14,'Review Items'!$B:$B,0)),IFERROR(INDEX('Rule Updates'!$C:$C,MATCH(C14,'Rule Updates'!$A:$A,0)),"Review")) | F14: 14.99 | G14: 119.28 | H14: 2 | I14: =IF(OR(D14="Uncategorised",E14=""),"Check","")
A15: Amex Sep-2024 | B15: 45536 | C15: CITYSUPER STORE @ AIRSI KOWLOON CITY | D15: =IFERROR(INDEX('Review Items'!$D:$D,MATCH(C15,'Review Items'!$B:$B,0)),IFERROR(INDEX('Rule Updates'!$B:$B,MATCH(C15,'Rule Updates'!$A:$A,0)),"Uncategorised")) | E15: =IFERROR(INDEX('Review Items'!$E:$E,MATCH(C15,'Review Items'!$B:$B,0)),IFERROR(INDEX('Rule Updates'!$C:$C,MATCH(C15,'Rule Updates'!$A:$A,0)),"Review")) | G15: 413.3 | H15: 2 | I15: =IF(OR(D15="Uncategorised",E15=""),"Check","")
A16: Amex Sep-2024 | B16: 45536 | C16: EIGHTH DAY SKINCA SANTA ANA | D16: =IFERROR(INDEX('Review Items'!$D:$D,MATCH(C16,'Review Items'!$B:$B,0)),IFERROR(INDEX('Rule Updates'!$B:$B,MATCH(C16,'Rule Updates'!$A:$A,0)),"Uncategorised")) | E16: =IFERROR(INDEX('Review Items'!$E:$E,MATCH(C16,'Review Items'!$B:$B,0)),IFERROR(INDEX('Rule Updates'!$C:$C,MATCH(C16,'Rule Updates'!$A:$A,0)),"Review")) | F16: 925.26 | G16: 7362.97 | H16: 2 | I16: =IF(OR(D16="Uncategorised",E16=""),"Check","")
A17: Amex Sep-2024 | B17: 45536 | C17: EIGHTH DAY SKINCA SANTA ANA | D17: =IFERROR(INDEX('Review Items'!$D:$D,MATCH(C17,'Review Items'!$B:$B,0)),IFERROR(INDEX('Rule Updates'!$B:$B,MATCH(C17,'Rule Updates'!$A:$A,0)),"Uncategorised")) | E17: =IFERROR(INDEX('Review Items'!$E:$E,MATCH(C17,'Review Items'!$B:$B,0)),IFERROR(INDEX('Rule Updates'!$C:$C,MATCH(C17,'Rule Updates'!$A:$A,0)),"Review")) | F17: 728.17 | G17: 5794.57 | H17: 2 | I17: =IF(OR(D17="Uncategorised",E17=""),"Check","")
A18: Amex Sep-2024 | B18: 45536 | C18: EIGHTH DAY SKINCA SANTA ANA | D18: =IFERROR(INDEX('Review Items'!$D:$D,MATCH(C18,'Review Items'!$B:$B,0)),IFERROR(INDEX('Rule Updates'!$B:$B,MATCH(C18,'Rule Updates'!$A:$A,0)),"Uncategorised")) | E18: =IFERROR(INDEX('Review Items'!$E:$E,MATCH(C18,'Review Items'!$B:$B,0)),IFERROR(INDEX('Rule Updates'!$C:$C,MATCH(C18,'Rule Updates'!$A:$A,0)),"Review")) | F18: 235.43 | G18: 1873.48 | H18: 2 | I18: =IF(OR(D18="Uncategorised",E18=""),"Check","")
A19: Amex Sep-2024 | B19: 45536 | C19: LOOKOPTIC LOS ANGELES | D19: =IFERROR(INDEX('Review Items'!$D:$D,MATCH(C19,'Review Items'!$B:$B,0)),IFERROR(INDEX('Rule Updates'!$B:$B,MATCH(C19,'Rule Updates'!$A:$A,0)),"Uncategorised")) | E19: =IFERROR(INDEX('Review Items'!$E:$E,MATCH(C19,'Review Items'!$B:$B,0)),IFERROR(INDEX('Rule Updates'!$C:$C,MATCH(C19,'Rule Updates'!$A:$A,0)),"Review")) | F19: 126.48 | G19: 1006.49 | H19: 2 | I19: =IF(OR(D19="Uncategorised",E19=""),"Check","")
A20: Amex Sep-2024 | B20: 45536 | C20: LOOKOPTIC LOS ANGELES | D20: =IFERROR(INDEX('Review Items'!$D:$D,MATCH(C20,'Review Items'!$B:$B,0)),IFERROR(INDEX('Rule Updates'!$B:$B,MATCH(C20,'Rule Updates'!$A:$A,0)),"Uncategorised")) | E20: =IFERROR(INDEX('Review Items'!$E:$E,MATCH(C20,'Review Items'!$B:$B,0)),IFERROR(INDEX('Rule Updates'!$C:$C,MATCH(C20,'Rule Updates'!$A:$A,0)),"Review")) | F20: 55.85 | G20: 444.43 | H20: 2 | I20: =IF(OR(D20="Uncategorised",E20=""),"Check","")
A21: Amex Sep-2024 | B21: 45537 | C21: APPLE.COM/BILL CUPERTINO | D21: =IFERROR(INDEX('Review Items'!$D:$D,MATCH(C21,'Review Items'!$B:$B,0)),IFERROR(INDEX('Rule Updates'!$B:$B,MATCH(C21,'Rule Updates'!$A:$A,0)),"Uncategorised")) | E21: =IFERROR(INDEX('Review Items'!$E:$E,MATCH(C21,'Review Items'!$B:$B,0)),IFERROR(INDEX('Rule Updates'!$C:$C,MATCH(C21,'Rule Updates'!$A:$A,0)),"Review")) | F21: 11.99 | G21: 95.37 | H21: 2 | I21: =IF(OR(D21="Uncategorised",E21=""),"Check","")
A22: Amex Sep-2024 | B22: 45538 | C22: AMAZON PRIME*7M54I5JM5 AMZN.CO.UK/PM | D22: =IFERROR(INDEX('Review Items'!$D:$D,MATCH(C22,'Review Items'!$B:$B,0)),IFERROR(INDEX('Rule Updates'!$B:$B,MATCH(C22,'Rule Updates'!$A:$A,0)),"Uncategorised")) | E22: =IFERROR(INDEX('Review Items'!$E:$E,MATCH(C22,'Review Items'!$B:$B,0)),IFERROR(INDEX('Rule Updates'!$C:$C,MATCH(C22,'Rule Updates'!$A:$A,0)),"Review")) | F22: 8.99 | G22: 94.09 | H22: 3 | I22: =IF(OR(D22="Uncategorised",E22=""),"Check","")
A23: Amex Sep-2024 | B23: 45538 | C23: CITY'SUPER CENTRAL | D23: =IFERROR(INDEX('Review Items'!$D:$D,MATCH(C23,'Review Items'!$B:$B,0)),IFERROR(INDEX('Rule Updates'!$B:$B,MATCH(C23,'Rule Updates'!$A:$A,0)),"Uncategorised")) | E23: =IFERROR(INDEX('Review Items'!$E:$E,MATCH(C23,'Review Items'!$B:$B,0)),IFERROR(INDEX('Rule Updates'!$C:$C,MATCH(C23,'Rule Updates'!$A:$A,0)),"Review")) | G23: 3308.2 | H23: 2 | I23: =IF(OR(D23="Uncategorised",E23=""),"Check","")
A24: Amex Sep-2024 | B24: 45540 | C24: MINDNLIFE LIMITED SUITE 1202 | D24: =IFERROR(INDEX('Review Items'!$D:$D,MATCH(C24,'Review Items'!$B:$B,0)),IFERROR(INDEX('Rule Updates'!$B:$B,MATCH(C24,'Rule Updates'!$A:$A,0)),"Uncategorised")) | E24: =IFERROR(INDEX('Review Items'!$E:$E,MATCH(C24,'Review Items'!$B:$B,0)),IFERROR(INDEX('Rule Updates'!$C:$C,MATCH(C24,'Rule Updates'!$A:$A,0)),"Review")) | G24: 2400 | H24: 3 | I24: =IF(OR(D24="Uncategorised",E24=""),"Check","")
A25: Amex Sep-2024 | B25: 45540 | C25: OUTDOOR VOICES AUSTIN | D25: =IFERROR(INDEX('Review Items'!$D:$D,MATCH(C25,'Review Items'!$B:$B,0)),IFERROR(INDEX('Rule Updates'!$B:$B,MATCH(C25,'Rule Updates'!$A:$A,0)),"Uncategorised")) | E25: =IFERROR(INDEX('Review Items'!$E:$E,MATCH(C25,'Review Items'!$B:$B,0)),IFERROR(INDEX('Rule Updates'!$C:$C,MATCH(C25,'Rule Updates'!$A:$A,0)),"Review")) | F25: 87.5 | G25: 695.83 | H25: 3 | I25: =IF(OR(D25="Uncategorised",E25=""),"Check","")
A26: Amex Sep-2024 | B26: 45540 | C26: PAYMENT RECEIVED THROUGH AUTOPAY | D26: =IFERROR(INDEX('Review Items'!$D:$D,MATCH(C26,'Review Items'!$B:$B,0)),IFERROR(INDEX('Rule Updates'!$B:$B,MATCH(C26,'Rule Updates'!$A:$A,0)),"Uncategorised")) | E26: =IFERROR(INDEX('Review Items'!$E:$E,MATCH(C26,'Review Items'!$B:$B,0)),IFERROR(INDEX('Rule Updates'!$C:$C,MATCH(C26,'Rule Updates'!$A:$A,0)),"Review")) | G26: -238651.88 | H26: 1 | I26: =IF(OR(D26="Uncategorised",E26=""),"Check","")
A27: Amex Sep-2024 | B27: 45541 | C27: ASIA MILES LIMITED HONG KONG | D27: =IFERROR(INDEX('Review Items'!$D:$D,MATCH(C27,'Review Items'!$B:$B,0)),IFERROR(INDEX('Rule Updates'!$B:$B,MATCH(C27,'Rule Updates'!$A:$A,0)),"Uncategorised")) | E27: =IFERROR(INDEX('Review Items'!$E:$E,MATCH(C27,'Review Items'!$B:$B,0)),IFERROR(INDEX('Rule Updates'!$C:$C,MATCH(C27,'Rule Updates'!$A:$A,0)),"Review")) | G27: -2733 | H27: 3 | I27: =IF(OR(D27="Uncategorised",E27=""),"Check","")
A28: Amex Sep-2024 | B28: 45545 | C28: AMAZON PRIME*BV1JF4LD5 AMZN.CO.UK/PM | D28: =IFERROR(INDEX('Review Items'!$D:$D,MATCH(C28,'Review Items'!$B:$B,0)),IFERROR(INDEX('Rule Updates'!$B:$B,MATCH(C28,'Rule Updates'!$A:$A,0)),"Uncategorised")) | E28: =IFERROR(INDEX('Review Items'!$E:$E,MATCH(C28,'Review Items'!$B:$B,0)),IFERROR(INDEX('Rule Updates'!$C:$C,MATCH(C28,'Rule Updates'!$A:$A,0)),"Review")) | F28: 8.99 | G28: 93.75 | H28: 3 | I28: =IF(OR(D28="Uncategorised",E28=""),"Check","")
A29: Amex Sep-2024 | B29: 45545 | C29: SILVERSEA LONDON | D29: =IFERROR(INDEX('Review Items'!$D:$D,MATCH(C29,'Review Items'!$B:$B,0)),IFERROR(INDEX('Rule Updates'!$B:$B,MATCH(C29,'Rule Updates'!$A:$A,0)),"Uncategorised")) | E29: =IFERROR(INDEX('Review Items'!$E:$E,MATCH(C29,'Review Items'!$B:$B,0)),IFERROR(INDEX('Rule Updates'!$C:$C,MATCH(C29,'Rule Updates'!$A:$A,0)),"Review")) | F29: 30250 | G29: 240598.03 | H29: 3 | I29: =IF(OR(D29="Uncategorised",E29=""),"Check","")
A30: Amex Sep-2024 | B30: 45545 | C30: SILVERSEA LONDON | D30: =IFERROR(INDEX('Review Items'!$D:$D,MATCH(C30,'Review Items'!$B:$B,0)),IFERROR(INDEX('Rule Updates'!$B:$B,MATCH(C30,'Rule Updates'!$A:$A,0)),"Uncategorised")) | E30: =IFERROR(INDEX('Review Items'!$E:$E,MATCH(C30,'Review Items'!$B:$B,0)),IFERROR(INDEX('Rule Updates'!$C:$C,MATCH(C30,'Rule Updates'!$A:$A,0)),"Review")) | F30: 24550 | G30: 195262.21 | H30: 3 | I30: =IF(OR(D30="Uncategorised",E30=""),"Check","")
A31: Amex Sep-2024 | B31: 45545 | C31: SILVERSEA LONDON | D31: =IFERROR(INDEX('Review Items'!$D:$D,MATCH(C31,'Review Items'!$B:$B,0)),IFERROR(INDEX('Rule Updates'!$B:$B,MATCH(C31,'Rule Updates'!$A:$A,0)),"Uncategorised")) | E31: =IFERROR(INDEX('Review Items'!$E:$E,MATCH(C31,'Review Items'!$B:$B,0)),IFERROR(INDEX('Rule Updates'!$C:$C,MATCH(C31,'Rule Updates'!$A:$A,0)),"Review")) | F31: 26050 | G31: 207192.69 | H31: 3 | I31: =IF(OR(D31="Uncategorised",E31=""),"Check","")
A32: Amex Sep-2024 | B32: 45545 | C32: SILVERSEA LONDON | D32: =IFERROR(INDEX('Review Items'!$D:$D,MATCH(C32,'Review Items'!$B:$B,0)),IFERROR(INDEX('Rule Updates'!$B:$B,MATCH(C32,'Rule Updates'!$A:$A,0)),"Uncategorised")) | E32: =IFERROR(INDEX('Review Items'!$E:$E,MATCH(C32,'Review Items'!$B:$B,0)),IFERROR(INDEX('Rule Updates'!$C:$C,MATCH(C32,'Rule Updates'!$A:$A,0)),"Review")) | F32: 26000 | G32: 206795 | H32: 3 | I32: =IF(OR(D32="Uncategorised",E32=""),"Check","")
A33: Amex Sep-2024 | B33: 45545 | C33: SILVERSEA LONDON | D33: =IFERROR(INDEX('Review Items'!$D:$D,MATCH(C33,'Review Items'!$B:$B,0)),IFERROR(INDEX('Rule Updates'!$B:$B,MATCH(C33,'Rule Updates'!$A:$A,0)),"Uncategorised")) | E33: =IFERROR(INDEX('Review Items'!$E:$E,MATCH(C33,'Review Items'!$B:$B,0)),IFERROR(INDEX('Rule Updates'!$C:$C,MATCH(C33,'Rule Updates'!$A:$A,0)),"Review")) | F33: 14290 | G33: 113657.71 | H33: 3 | I33: =IF(OR(D33="Uncategorised",E33=""),"Check","")
A34: Amex Sep-2024 | B34: 45545 | C34: SILVERSEA LONDON | D34: =IFERROR(INDEX('Review Items'!$D:$D,MATCH(C34,'Review Items'!$B:$B,0)),IFERROR(INDEX('Rule Updates'!$B:$B,MATCH(C34,'Rule Updates'!$A:$A,0)),"Uncategorised")) | E34: =IFERROR(INDEX('Review Items'!$E:$E,MATCH(C34,'Review Items'!$B:$B,0)),IFERROR(INDEX('Rule Updates'!$C:$C,MATCH(C34,'Rule Updates'!$A:$A,0)),"Review")) | F34: 26050 | G34: 207192.69 | H34: 3 | I34: =IF(OR(D34="Uncategorised",E34=""),"Check","")
A35: Amex Sep-2024 | B35: 45545 | C35: SILVERSEA LONDON | D35: =IFERROR(INDEX('Review Items'!$D:$D,MATCH(C35,'Review Items'!$B:$B,0)),IFERROR(INDEX('Rule Updates'!$B:$B,MATCH(C35,'Rule Updates'!$A:$A,0)),"Uncategorised")) | E35: =IFERROR(INDEX('Review Items'!$E:$E,MATCH(C35,'Review Items'!$B:$B,0)),IFERROR(INDEX('Rule Updates'!$C:$C,MATCH(C35,'Rule Updates'!$A:$A,0)),"Review")) | F35: 2112 | G35: 16798.11 | H35: 3 | I35: =IF(OR(D35="Uncategorised",E35=""),"Check","")
A36: Amex Sep-2024 | B36: 45545 | C36: SILVERSEA LONDON | D36: =IFERROR(INDEX('Review Items'!$D:$D,MATCH(C36,'Review Items'!$B:$B,0)),IFERROR(INDEX('Rule Updates'!$B:$B,MATCH(C36,'Rule Updates'!$A:$A,0)),"Uncategorised")) | E36: =IFERROR(INDEX('Review Items'!$E:$E,MATCH(C36,'Review Items'!$B:$B,0)),IFERROR(INDEX('Rule Updates'!$C:$C,MATCH(C36,'Rule Updates'!$A:$A,0)),"Review")) | F36: 11968 | G36: 95189.32 | H36: 3 | I36: =IF(OR(D36="Uncategorised",E36=""),"Check","")
A37: Amex Sep-2024 | B37: 45546 | C37: BAR LEONE SHEUNG WAN | D37: =IFERROR(INDEX('Review Items'!$D:$D,MATCH(C37,'Review Items'!$B:$B,0)),IFERROR(INDEX('Rule Updates'!$B:$B,MATCH(C37,'Rule Updates'!$A:$A,0)),"Uncategorised")) | E37: =IFERROR(INDEX('Review Items'!$E:$E,MATCH(C37,'Review Items'!$B:$B,0)),IFERROR(INDEX('Rule Updates'!$C:$C,MATCH(C37,'Rule Updates'!$A:$A,0)),"Review")) | G37: 2963 | H37: 3 | I37: =IF(OR(D37="Uncategorised",E37=""),"Check","")
A38: Amex Sep-2024 | B38: 45546 | C38: GARMIN (EUROPE) LIMITED SOUTHAMPTON | D38: =IFERROR(INDEX('Review Items'!$D:$D,MATCH(C38,'Review Items'!$B:$B,0)),IFERROR(INDEX('Rule Updates'!$B:$B,MATCH(C38,'Rule Updates'!$A:$A,0)),"Uncategorised")) | E38: =IFERROR(INDEX('Review Items'!$E:$E,MATCH(C38,'Review Items'!$B:$B,0)),IFERROR(INDEX('Rule Updates'!$C:$C,MATCH(C38,'Rule Updates'!$A:$A,0)),"Review")) | F38: 9.99 | G38: 79.45 | H38: 3 | I38: =IF(OR(D38="Uncategorised",E38=""),"Check","")
A39: Amex Sep-2024 | B39: 45546 | C39: KITH Cafe ASCOTT ORCHAR SINGAPORE | D39: =IFERROR(INDEX('Review Items'!$D:$D,MATCH(C39,'Review Items'!$B:$B,0)),IFERROR(INDEX('Rule Updates'!$B:$B,MATCH(C39,'Rule Updates'!$A:$A,0)),"Uncategorised")) | E39: =IFERROR(INDEX('Review Items'!$E:$E,MATCH(C39,'Review Items'!$B:$B,0)),IFERROR(INDEX('Rule Updates'!$C:$C,MATCH(C39,'Rule Updates'!$A:$A,0)),"Review")) | F39: 22.13 | G39: 134.96 | H39: 6 | I39: =IF(OR(D39="Uncategorised",E39=""),"Check","")
A40: Amex Sep-2024 | B40: 45546 | C40: KITH Cafe ASCOTT ORCHAR SINGAPORE | D40: =IFERROR(INDEX('Review Items'!$D:$D,MATCH(C40,'Review Items'!$B:$B,0)),IFERROR(INDEX('Rule Updates'!$B:$B,MATCH(C40,'Rule Updates'!$A:$A,0)),"Uncategorised")) | E40: =IFERROR(INDEX('Review Items'!$E:$E,MATCH(C40,'Review Items'!$B:$B,0)),IFERROR(INDEX('Rule Updates'!$C:$C,MATCH(C40,'Rule Updates'!$A:$A,0)),"Review")) | F40: 7.14 | G40: 43.58 | H40: 6 | I40: =IF(OR(D40="Uncategorised",E40=""),"Check","")
A41: Amex Sep-2024 | B41: 45546 | C41: KPAY*MOMOGAWANOU 000000 HONG KONG | D41: =IFERROR(INDEX('Review Items'!$D:$D,MATCH(C41,'Review Items'!$B:$B,0)),IFERROR(INDEX('Rule Updates'!$B:$B,MATCH(C41,'Rule Updates'!$A:$A,0)),"Uncategorised")) | E41: =IFERROR(INDEX('Review Items'!$E:$E,MATCH(C41,'Review Items'!$B:$B,0)),IFERROR(INDEX('Rule Updates'!$C:$C,MATCH(C41,'Rule Updates'!$A:$A,0)),"Review")) | G41: 3340 | H41: 4 | I41: =IF(OR(D41="Uncategorised",E41=""),"Check","")
A42: Amex Sep-2024 | B42: 45546 | C42: SOLACE LONDON LONDON | D42: =IFERROR(INDEX('Review Items'!$D:$D,MATCH(C42,'Review Items'!$B:$B,0)),IFERROR(INDEX('Rule Updates'!$B:$B,MATCH(C42,'Rule Updates'!$A:$A,0)),"Uncategorised")) | E42: =IFERROR(INDEX('Review Items'!$E:$E,MATCH(C42,'Review Items'!$B:$B,0)),IFERROR(INDEX('Rule Updates'!$C:$C,MATCH(C42,'Rule Updates'!$A:$A,0)),"Review")) | F42: 645 | G42: 6725.57 | H42: 3 | I42: =IF(OR(D42="Uncategorised",E42=""),"Check","")
A43: Amex Sep-2024 | B43: 45546 | C43: UNIQLO HONG KONG LIMITE TSIM SHA TSUI | D43: =IFERROR(INDEX('Review Items'!$D:$D,MATCH(C43,'Review Items'!$B:$B,0)),IFERROR(INDEX('Rule Updates'!$B:$B,MATCH(C43,'Rule Updates'!$A:$A,0)),"Uncategorised")) | E43: =IFERROR(INDEX('Review Items'!$E:$E,MATCH(C43,'Review Items'!$B:$B,0)),IFERROR(INDEX('Rule Updates'!$C:$C,MATCH(C43,'Rule Updates'!$A:$A,0)),"Review")) | G43: 229 | H43: 3 | I43: =IF(OR(D43="Uncategorised",E43=""),"Check","")
A44: Amex Sep-2024 | B44: 45547 | C44: FARFETCH LONDON | D44: =IFERROR(INDEX('Review Items'!$D:$D,MATCH(C44,'Review Items'!$B:$B,0)),IFERROR(INDEX('Rule Updates'!$B:$B,MATCH(C44,'Rule Updates'!$A:$A,0)),"Uncategorised")) | E44: =IFERROR(INDEX('Review Items'!$E:$E,MATCH(C44,'Review Items'!$B:$B,0)),IFERROR(INDEX('Rule Updates'!$C:$C,MATCH(C44,'Rule Updates'!$A:$A,0)),"Review")) | G44: 25033 | H44: 4 | I44: =IF(OR(D44="Uncategorised",E44=""),"Check","")
A45: Amex Sep-2024 | B45: 45547 | C45: SHIMBASHI SOBA - PARAGO SINGAPORE | D45: =IFERROR(INDEX('Review Items'!$D:$D,MATCH(C45,'Review Items'!$B:$B,0)),IFERROR(INDEX('Rule Updates'!$B:$B,MATCH(C45,'Rule Updates'!$A:$A,0)),"Uncategorised")) | E45: =IFERROR(INDEX('Review Items'!$E:$E,MATCH(C45,'Review Items'!$B:$B,0)),IFERROR(INDEX('Rule Updates'!$C:$C,MATCH(C45,'Rule Updates'!$A:$A,0)),"Review")) | F45: 120.26 | G45: 735.44 | H45: 4 | I45: =IF(OR(D45="Uncategorised",E45=""),"Check","")
A46: Amex Sep-2024 | B46: 45547 | C46: THE DAIRY FARM - MANNIN LANTAU | D46: =IFERROR(INDEX('Review Items'!$D:$D,MATCH(C46,'Review Items'!$B:$B,0)),IFERROR(INDEX('Rule Updates'!$B:$B,MATCH(C46,'Rule Updates'!$A:$A,0)),"Uncategorised")) | E46: =IFERROR(INDEX('Review Items'!$E:$E,MATCH(C46,'Review Items'!$B:$B,0)),IFERROR(INDEX('Rule Updates'!$C:$C,MATCH(C46,'Rule Updates'!$A:$A,0)),"Review")) | G46: 549 | H46: 4 | I46: =IF(OR(D46="Uncategorised",E46=""),"Check","")
A47: Amex Sep-2024 | B47: 45548 | C47: APPLE.COM/BILL CUPERTINO | D47: =IFERROR(INDEX('Review Items'!$D:$D,MATCH(C47,'Review Items'!$B:$B,0)),IFERROR(INDEX('Rule Updates'!$B:$B,MATCH(C47,'Rule Updates'!$A:$A,0)),"Uncategorised")) | E47: =IFERROR(INDEX('Review Items'!$E:$E,MATCH(C47,'Review Items'!$B:$B,0)),IFERROR(INDEX('Rule Updates'!$C:$C,MATCH(C47,'Rule Updates'!$A:$A,0)),"Review")) | F47: 11.99 | G47: 95.44 | H47: 4 | I47: =IF(OR(D47="Uncategorised",E47=""),"Check","")
A48: Amex Sep-2024 | B48: 45548 | C48: APPLE.COM/BILL CUPERTINO | D48: =IFERROR(INDEX('Review Items'!$D:$D,MATCH(C48,'Review Items'!$B:$B,0)),IFERROR(INDEX('Rule Updates'!$B:$B,MATCH(C48,'Rule Updates'!$A:$A,0)),"Uncategorised")) | E48: =IFERROR(INDEX('Review Items'!$E:$E,MATCH(C48,'Review Items'!$B:$B,0)),IFERROR(INDEX('Rule Updates'!$C:$C,MATCH(C48,'Rule Updates'!$A:$A,0)),"Review")) | F48: 37.95 | G48: 302.07 | H48: 4 | I48: =IF(OR(D48="Uncategorised",E48=""),"Check","")
A49: Amex Sep-2024 | B49: 45548 | C49: COLD STORAGE FRESH KIM SINGAPORE | D49: =IFERROR(INDEX('Review Items'!$D:$D,MATCH(C49,'Review Items'!$B:$B,0)),IFERROR(INDEX('Rule Updates'!$B:$B,MATCH(C49,'Rule Updates'!$A:$A,0)),"Uncategorised")) | E49: =IFERROR(INDEX('Review Items'!$E:$E,MATCH(C49,'Review Items'!$B:$B,0)),IFERROR(INDEX('Rule Updates'!$C:$C,MATCH(C49,'Rule Updates'!$A:$A,0)),"Review")) | F49: 2.45 | G49: 14.96 | H49: 4 | I49: =IF(OR(D49="Uncategorised",E49=""),"Check","")
A50: Amex Sep-2024 | B50: 45548 | C50: GRAB*A-6T3KP6GWWFFO SINGAPORE | D50: =IFERROR(INDEX('Review Items'!$D:$D,MATCH(C50,'Review Items'!$B:$B,0)),IFERROR(INDEX('Rule Updates'!$B:$B,MATCH(C50,'Rule Updates'!$A:$A,0)),"Uncategorised")) | E50: =IFERROR(INDEX('Review Items'!$E:$E,MATCH(C50,'Review Items'!$B:$B,0)),IFERROR(INDEX('Rule Updates'!$C:$C,MATCH(C50,'Rule Updates'!$A:$A,0)),"Review")) | F50: 26.88 | G50: 164.19 | H50: 4 | I50: =IF(OR(D50="Uncategorised",E50=""),"Check","")
A51: Amex Sep-2024 | B51: 45548 | C51: SEROJA SINGAPORE | D51: =IFERROR(INDEX('Review Items'!$D:$D,MATCH(C51,'Review Items'!$B:$B,0)),IFERROR(INDEX('Rule Updates'!$B:$B,MATCH(C51,'Rule Updates'!$A:$A,0)),"Uncategorised")) | E51: =IFERROR(INDEX('Review Items'!$E:$E,MATCH(C51,'Review Items'!$B:$B,0)),IFERROR(INDEX('Rule Updates'!$C:$C,MATCH(C51,'Rule Updates'!$A:$A,0)),"Review")) | F51: 1662.28 | G51: 10152.1 | H51: 6 | I51: =IF(OR(D51="Uncategorised",E51=""),"Check","")
A52: Amex Sep-2024 | B52: 45549 | C52: PENINSULA HK - F&BTSIMSHATSUI | D52: =IFERROR(INDEX('Review Items'!$D:$D,MATCH(C52,'Review Items'!$B:$B,0)),IFERROR(INDEX('Rule Updates'!$B:$B,MATCH(C52,'Rule Updates'!$A:$A,0)),"Uncategorised")) | E52: =IFERROR(INDEX('Review Items'!$E:$E,MATCH(C52,'Review Items'!$B:$B,0)),IFERROR(INDEX('Rule Updates'!$C:$C,MATCH(C52,'Rule Updates'!$A:$A,0)),"Review")) | G52: 4968 | H52: 6 | I52: =IF(OR(D52="Uncategorised",E52=""),"Check","")
A53: Amex Sep-2024 | B53: 45549 | C53: THE COCONUT Club - KIM SINGAPORE | D53: =IFERROR(INDEX('Review Items'!$D:$D,MATCH(C53,'Review Items'!$B:$B,0)),IFERROR(INDEX('Rule Updates'!$B:$B,MATCH(C53,'Rule Updates'!$A:$A,0)),"Uncategorised")) | E53: =IFERROR(INDEX('Review Items'!$E:$E,MATCH(C53,'Review Items'!$B:$B,0)),IFERROR(INDEX('Rule Updates'!$C:$C,MATCH(C53,'Rule Updates'!$A:$A,0)),"Review")) | F53: 71.94 | G53: 441.17 | H53: 4 | I53: =IF(OR(D53="Uncategorised",E53=""),"Check","")
A54: Amex Sep-2024 | B54: 45549 | C54: THE COCONUT Club - KIM SINGAPORE | D54: =IFERROR(INDEX('Review Items'!$D:$D,MATCH(C54,'Review Items'!$B:$B,0)),IFERROR(INDEX('Rule Updates'!$B:$B,MATCH(C54,'Rule Updates'!$A:$A,0)),"Uncategorised")) | E54: =IFERROR(INDEX('Review Items'!$E:$E,MATCH(C54,'Review Items'!$B:$B,0)),IFERROR(INDEX('Rule Updates'!$C:$C,MATCH(C54,'Rule Updates'!$A:$A,0)),"Review")) | F54: 17.44 | G54: 106.98 | H54: 4 | I54: =IF(OR(D54="Uncategorised",E54=""),"Check","")
A55: Amex Sep-2024 | B55: 45550 | C55: APPLE.COM/BILL CUPERTINO | D55: =IFERROR(INDEX('Review Items'!$D:$D,MATCH(C55,'Review Items'!$B:$B,0)),IFERROR(INDEX('Rule Updates'!$B:$B,MATCH(C55,'Rule Updates'!$A:$A,0)),"Uncategorised")) | E55: =IFERROR(INDEX('Review Items'!$E:$E,MATCH(C55,'Review Items'!$B:$B,0)),IFERROR(INDEX('Rule Updates'!$C:$C,MATCH(C55,'Rule Updates'!$A:$A,0)),"Review")) | F55: 3.49 | G55: 27.76 | H55: 4 | I55: =IF(OR(D55="Uncategorised",E55=""),"Check","")
A56: Amex Sep-2024 | B56: 45551 | C56: HTL*ASCOTTORCHARDS 800-468-3578 | D56: =IFERROR(INDEX('Review Items'!$D:$D,MATCH(C56,'Review Items'!$B:$B,0)),IFERROR(INDEX('Rule Updates'!$B:$B,MATCH(C56,'Rule Updates'!$A:$A,0)),"Uncategorised")) | E56: =IFERROR(INDEX('Review Items'!$E:$E,MATCH(C56,'Review Items'!$B:$B,0)),IFERROR(INDEX('Rule Updates'!$C:$C,MATCH(C56,'Rule Updates'!$A:$A,0)),"Review")) | F56: 16347.65 | G56: 130066.9 | H56: 6 | I56: =IF(OR(D56="Uncategorised",E56=""),"Check","")
A57: Amex Sep-2024 | B57: 45551 | C57: LANE CRAWFORD (IFC) CENTRAL | D57: =IFERROR(INDEX('Review Items'!$D:$D,MATCH(C57,'Review Items'!$B:$B,0)),IFERROR(INDEX('Rule Updates'!$B:$B,MATCH(C57,'Rule Updates'!$A:$A,0)),"Uncategorised")) | E57: =IFERROR(INDEX('Review Items'!$E:$E,MATCH(C57,'Review Items'!$B:$B,0)),IFERROR(INDEX('Rule Updates'!$C:$C,MATCH(C57,'Rule Updates'!$A:$A,0)),"Review")) | G57: 860 | H57: 4 | I57: =IF(OR(D57="Uncategorised",E57=""),"Check","")
A58: Amex Sep-2024 | B58: 45552 | C58: CITY'SUPER CENTRAL | D58: =IFERROR(INDEX('Review Items'!$D:$D,MATCH(C58,'Review Items'!$B:$B,0)),IFERROR(INDEX('Rule Updates'!$B:$B,MATCH(C58,'Rule Updates'!$A:$A,0)),"Uncategorised")) | E58: =IFERROR(INDEX('Review Items'!$E:$E,MATCH(C58,'Review Items'!$B:$B,0)),IFERROR(INDEX('Rule Updates'!$C:$C,MATCH(C58,'Rule Updates'!$A:$A,0)),"Review")) | G58: 447.2 | H58: 4 | I58: =IF(OR(D58="Uncategorised",E58=""),"Check","")
A59: Amex Sep-2024 | B59: 45554 | C59: APPLE.COM/BILL CUPERTINO | D59: =IFERROR(INDEX('Review Items'!$D:$D,MATCH(C59,'Review Items'!$B:$B,0)),IFERROR(INDEX('Rule Updates'!$B:$B,MATCH(C59,'Rule Updates'!$A:$A,0)),"Uncategorised")) | E59: =IFERROR(INDEX('Review Items'!$E:$E,MATCH(C59,'Review Items'!$B:$B,0)),IFERROR(INDEX('Rule Updates'!$C:$C,MATCH(C59,'Rule Updates'!$A:$A,0)),"Review")) | F59: 4.99 | G59: 39.67 | H59: 4 | I59: =IF(OR(D59="Uncategorised",E59=""),"Check","")
A60: Amex Sep-2024 | B60: 45556 | C60: CATHAY PACIFIC AIRWAYS HONG KONG | D60: =IFERROR(INDEX('Review Items'!$D:$D,MATCH(C60,'Review Items'!$B:$B,0)),IFERROR(INDEX('Rule Updates'!$B:$B,MATCH(C60,'Rule Updates'!$A:$A,0)),"Uncategorised")) | E60: =IFERROR(INDEX('Review Items'!$E:$E,MATCH(C60,'Review Items'!$B:$B,0)),IFERROR(INDEX('Rule Updates'!$C:$C,MATCH(C60,'Rule Updates'!$A:$A,0)),"Review")) | G60: 5679 | H60: 6 | I60: =IF(OR(D60="Uncategorised",E60=""),"Check","")
A61: Amex Sep-2024 | B61: 45557 | C61: KATES BREAD OJAI | D61: =IFERROR(INDEX('Review Items'!$D:$D,MATCH(C61,'Review Items'!$B:$B,0)),IFERROR(INDEX('Rule Updates'!$B:$B,MATCH(C61,'Rule Updates'!$A:$A,0)),"Uncategorised")) | E61: =IFERROR(INDEX('Review Items'!$E:$E,MATCH(C61,'Review Items'!$B:$B,0)),IFERROR(INDEX('Rule Updates'!$C:$C,MATCH(C61,'Rule Updates'!$A:$A,0)),"Review")) | F61: 5 | G61: 39.74 | H61: 4 | I61: =IF(OR(D61="Uncategorised",E61=""),"Check","")
A62: Amex Sep-2024 | B62: 45559 | C62: CITYSUPER STORE @ SOUTH WONG CHUK HANG | D62: =IFERROR(INDEX('Review Items'!$D:$D,MATCH(C62,'Review Items'!$B:$B,0)),IFERROR(INDEX('Rule Updates'!$B:$B,MATCH(C62,'Rule Updates'!$A:$A,0)),"Uncategorised")) | E62: =IFERROR(INDEX('Review Items'!$E:$E,MATCH(C62,'Review Items'!$B:$B,0)),IFERROR(INDEX('Rule Updates'!$C:$C,MATCH(C62,'Rule Updates'!$A:$A,0)),"Review")) | G62: 943.1 | H62: 4 | I62: =IF(OR(D62="Uncategorised",E62=""),"Check","")
A63: Amex Sep-2024 | B63: 45559 | C63: SP SOLACE LONDON LONDON | D63: =IFERROR(INDEX('Review Items'!$D:$D,MATCH(C63,'Review Items'!$B:$B,0)),IFERROR(INDEX('Rule Updates'!$B:$B,MATCH(C63,'Rule Updates'!$A:$A,0)),"Uncategorised")) | E63: =IFERROR(INDEX('Review Items'!$E:$E,MATCH(C63,'Review Items'!$B:$B,0)),IFERROR(INDEX('Rule Updates'!$C:$C,MATCH(C63,'Rule Updates'!$A:$A,0)),"Review")) | F63: 620 | G63: -6468.3 | H63: 4 | I63: =IF(OR(D63="Uncategorised",E63=""),"Check","")
A64: Amex Sep-2024 | B64: 45560 | C64: KPAY*GALLERY TETE HONG HONG KONG | D64: =IFERROR(INDEX('Review Items'!$D:$D,MATCH(C64,'Review Items'!$B:$B,0)),IFERROR(INDEX('Rule Updates'!$B:$B,MATCH(C64,'Rule Updates'!$A:$A,0)),"Uncategorised")) | E64: =IFERROR(INDEX('Review Items'!$E:$E,MATCH(C64,'Review Items'!$B:$B,0)),IFERROR(INDEX('Rule Updates'!$C:$C,MATCH(C64,'Rule Updates'!$A:$A,0)),"Review")) | G64: 1900 | H64: 4 | I64: =IF(OR(D64="Uncategorised",E64=""),"Check","")
A65: Amex Sep-2024 | B65: 45560 | C65: SPLASH FOUNDATION LIMI SINGAPORE | D65: =IFERROR(INDEX('Review Items'!$D:$D,MATCH(C65,'Review Items'!$B:$B,0)),IFERROR(INDEX('Rule Updates'!$B:$B,MATCH(C65,'Rule Updates'!$A:$A,0)),"Uncategorised")) | E65: =IFERROR(INDEX('Review Items'!$E:$E,MATCH(C65,'Review Items'!$B:$B,0)),IFERROR(INDEX('Rule Updates'!$C:$C,MATCH(C65,'Rule Updates'!$A:$A,0)),"Review")) | G65: 51000 | H65: 5 | I65: =IF(OR(D65="Uncategorised",E65=""),"Check","")
A66: Amex Sep-2024 | B66: 45561 | C66: ANNUAL FEE | D66: =IFERROR(INDEX('Review Items'!$D:$D,MATCH(C66,'Review Items'!$B:$B,0)),IFERROR(INDEX('Rule Updates'!$B:$B,MATCH(C66,'Rule Updates'!$A:$A,0)),"Uncategorised")) | E66: =IFERROR(INDEX('Review Items'!$E:$E,MATCH(C66,'Review Items'!$B:$B,0)),IFERROR(INDEX('Rule Updates'!$C:$C,MATCH(C66,'Rule Updates'!$A:$A,0)),"Review")) | G66: 38800 | H66: 7 | I66: =IF(OR(D66="Uncategorised",E66=""),"Check","")
A67: Amex Oct-2024 | B67: 45561 | C67: SILVERSEA LONDON | D67: =IFERROR(INDEX('Review Items'!$D:$D,MATCH(C67,'Review Items'!$B:$B,0)),IFERROR(INDEX('Rule Updates'!$B:$B,MATCH(C67,'Rule Updates'!$A:$A,0)),"Uncategorised")) | E67: =IFERROR(INDEX('Review Items'!$E:$E,MATCH(C67,'Review Items'!$B:$B,0)),IFERROR(INDEX('Rule Updates'!$C:$C,MATCH(C67,'Rule Updates'!$A:$A,0)),"Review")) | F67: 9690 | G67: 76942.41 | H67: 1 | I67: =IF(OR(D67="Uncategorised",E67=""),"Check","")
A68: Amex Oct-2024 | B68: 45561 | C68: SILVERSEA LONDON | D68: =IFERROR(INDEX('Review Items'!$D:$D,MATCH(C68,'Review Items'!$B:$B,0)),IFERROR(INDEX('Rule Updates'!$B:$B,MATCH(C68,'Rule Updates'!$A:$A,0)),"Uncategorised")) | E68: =IFERROR(INDEX('Review Items'!$E:$E,MATCH(C68,'Review Items'!$B:$B,0)),IFERROR(INDEX('Rule Updates'!$C:$C,MATCH(C68,'Rule Updates'!$A:$A,0)),"Review")) | F68: 13680 | G68: 108624.59 | H68: 1 | I68: =IF(OR(D68="Uncategorised",E68=""),"Check","")
A69: Amex Oct-2024 | B69: 45561 | C69: SILVERSEA LONDON | D69: =IFERROR(INDEX('Review Items'!$D:$D,MATCH(C69,'Review Items'!$B:$B,0)),IFERROR(INDEX('Rule Updates'!$B:$B,MATCH(C69,'Rule Updates'!$A:$A,0)),"Uncategorised")) | E69: =IFERROR(INDEX('Review Items'!$E:$E,MATCH(C69,'Review Items'!$B:$B,0)),IFERROR(INDEX('Rule Updates'!$C:$C,MATCH(C69,'Rule Updates'!$A:$A,0)),"Review")) | F69: 10260 | G69: 81468.44 | H69: 1 | I69: =IF(OR(D69="Uncategorised",E69=""),"Check","")
A70: Amex Oct-2024 | B70: 45562 | C70: FARFETCH LONDON | D70: =IFERROR(INDEX('Review Items'!$D:$D,MATCH(C70,'Review Items'!$B:$B,0)),IFERROR(INDEX('Rule Updates'!$B:$B,MATCH(C70,'Rule Updates'!$A:$A,0)),"Uncategorised")) | E70: =IFERROR(INDEX('Review Items'!$E:$E,MATCH(C70,'Review Items'!$B:$B,0)),IFERROR(INDEX('Rule Updates'!$C:$C,MATCH(C70,'Rule Updates'!$A:$A,0)),"Review")) | G70: -5712 | H70: 1 | I70: =IF(OR(D70="Uncategorised",E70=""),"Check","")
A71: Amex Oct-2024 | B71: 45562 | C71: SA SA (HA02) CAUSEWAY BAY | D71: =IFERROR(INDEX('Review Items'!$D:$D,MATCH(C71,'Review Items'!$B:$B,0)),IFERROR(INDEX('Rule Updates'!$B:$B,MATCH(C71,'Rule Updates'!$A:$A,0)),"Uncategorised")) | E71: =IFERROR(INDEX('Review Items'!$E:$E,MATCH(C71,'Review Items'!$B:$B,0)),IFERROR(INDEX('Rule Updates'!$C:$C,MATCH(C71,'Rule Updates'!$A:$A,0)),"Review")) | G71: 453.6 | H71: 1 | I71: =IF(OR(D71="Uncategorised",E71=""),"Check","")
A72: Amex Oct-2024 | B72: 45562 | C72: SILVERSEA LONDON | D72: =IFERROR(INDEX('Review Items'!$D:$D,MATCH(C72,'Review Items'!$B:$B,0)),IFERROR(INDEX('Rule Updates'!$B:$B,MATCH(C72,'Rule Updates'!$A:$A,0)),"Uncategorised")) | E72: =IFERROR(INDEX('Review Items'!$E:$E,MATCH(C72,'Review Items'!$B:$B,0)),IFERROR(INDEX('Rule Updates'!$C:$C,MATCH(C72,'Rule Updates'!$A:$A,0)),"Review")) | F72: 6000 | G72: 47618.49 | H72: 2 | I72: =IF(OR(D72="Uncategorised",E72=""),"Check","")
A73: Amex Oct-2024 | B73: 45562 | C73: SOGO HK LTD - SUPERMARK CAUSEWAY BAY | D73: =IFERROR(INDEX('Review Items'!$D:$D,MATCH(C73,'Review Items'!$B:$B,0)),IFERROR(INDEX('Rule Updates'!$B:$B,MATCH(C73,'Rule Updates'!$A:$A,0)),"Uncategorised")) | E73: =IFERROR(INDEX('Review Items'!$E:$E,MATCH(C73,'Review Items'!$B:$B,0)),IFERROR(INDEX('Rule Updates'!$C:$C,MATCH(C73,'Rule Updates'!$A:$A,0)),"Review")) | G73: 360 | H73: 1 | I73: =IF(OR(D73="Uncategorised",E73=""),"Check","")
A74: Amex Oct-2024 | B74: 45562 | C74: SOGO HONG KONG CO LTD CAUSEWAY BAY | D74: =IFERROR(INDEX('Review Items'!$D:$D,MATCH(C74,'Review Items'!$B:$B,0)),IFERROR(INDEX('Rule Updates'!$B:$B,MATCH(C74,'Rule Updates'!$A:$A,0)),"Uncategorised")) | E74: =IFERROR(INDEX('Review Items'!$E:$E,MATCH(C74,'Review Items'!$B:$B,0)),IFERROR(INDEX('Rule Updates'!$C:$C,MATCH(C74,'Rule Updates'!$A:$A,0)),"Review")) | G74: 120 | H74: 2 | I74: =IF(OR(D74="Uncategorised",E74=""),"Check","")
A75: Amex Oct-2024 | B75: 45563 | C75: THE CHINNERY BAR CENTRAL | D75: =IFERROR(INDEX('Review Items'!$D:$D,MATCH(C75,'Review Items'!$B:$B,0)),IFERROR(INDEX('Rule Updates'!$B:$B,MATCH(C75,'Rule Updates'!$A:$A,0)),"Uncategorised")) | E75: =IFERROR(INDEX('Review Items'!$E:$E,MATCH(C75,'Review Items'!$B:$B,0)),IFERROR(INDEX('Rule Updates'!$C:$C,MATCH(C75,'Rule Updates'!$A:$A,0)),"Review")) | G75: 2080 | H75: 5 | I75: =IF(OR(D75="Uncategorised",E75=""),"Check","")
A76: Amex Oct-2024 | B76: 45566 | C76: AMAZON PRIME*A396O4Q43 AMZN.COM/BILL | D76: =IFERROR(INDEX('Review Items'!$D:$D,MATCH(C76,'Review Items'!$B:$B,0)),IFERROR(INDEX('Rule Updates'!$B:$B,MATCH(C76,'Rule Updates'!$A:$A,0)),"Uncategorised")) | E76: =IFERROR(INDEX('Review Items'!$E:$E,MATCH(C76,'Review Items'!$B:$B,0)),IFERROR(INDEX('Rule Updates'!$C:$C,MATCH(C76,'Rule Updates'!$A:$A,0)),"Review")) | F76: 14.99 | G76: 118.78 | H76: 2 | I76: =IF(OR(D76="Uncategorised",E76=""),"Check","")
A77: Amex Oct-2024 | B77: 45567 | C77: FARFETCH LONDON | D77: =IFERROR(INDEX('Review Items'!$D:$D,MATCH(C77,'Review Items'!$B:$B,0)),IFERROR(INDEX('Rule Updates'!$B:$B,MATCH(C77,'Rule Updates'!$A:$A,0)),"Uncategorised")) | E77: =IFERROR(INDEX('Review Items'!$E:$E,MATCH(C77,'Review Items'!$B:$B,0)),IFERROR(INDEX('Rule Updates'!$C:$C,MATCH(C77,'Rule Updates'!$A:$A,0)),"Review")) | G77: -7391 | H77: 2 | I77: =IF(OR(D77="Uncategorised",E77=""),"Check","")
A78: Amex Oct-2024 | B78: 45568 | C78: AMAZON PRIME*TA1M20WO4 AMZN.CO.UK/PM | D78: =IFERROR(INDEX('Review Items'!$D:$D,MATCH(C78,'Review Items'!$B:$B,0)),IFERROR(INDEX('Rule Updates'!$B:$B,MATCH(C78,'Rule Updates'!$A:$A,0)),"Uncategorised")) | E78: =IFERROR(INDEX('Review Items'!$E:$E,MATCH(C78,'Review Items'!$B:$B,0)),IFERROR(INDEX('Rule Updates'!$C:$C,MATCH(C78,'Rule Updates'!$A:$A,0)),"Review")) | F78: 8.99 | G78: 94.72 | H78: 2 | I78: =IF(OR(D78="Uncategorised",E78=""),"Check","")
A79: Amex Oct-2024 | B79: 45570 | C79: AMZNMKTPLACE*TO11Y8184 AMAZON.CO.UK | D79: =IFERROR(INDEX('Review Items'!$D:$D,MATCH(C79,'Review Items'!$B:$B,0)),IFERROR(INDEX('Rule Updates'!$B:$B,MATCH(C79,'Rule Updates'!$A:$A,0)),"Uncategorised")) | E79: =IFERROR(INDEX('Review Items'!$E:$E,MATCH(C79,'Review Items'!$B:$B,0)),IFERROR(INDEX('Rule Updates'!$C:$C,MATCH(C79,'Rule Updates'!$A:$A,0)),"Review")) | G79: 535.51 | H79: 2 | I79: =IF(OR(D79="Uncategorised",E79=""),"Check","")
A80: Amex Oct-2024 | B80: 45571 | C80: HTL*ASCOTTORCHARDS 800-468-3578 | D80: =IFERROR(INDEX('Review Items'!$D:$D,MATCH(C80,'Review Items'!$B:$B,0)),IFERROR(INDEX('Rule Updates'!$B:$B,MATCH(C80,'Rule Updates'!$A:$A,0)),"Uncategorised")) | E80: =IFERROR(INDEX('Review Items'!$E:$E,MATCH(C80,'Review Items'!$B:$B,0)),IFERROR(INDEX('Rule Updates'!$C:$C,MATCH(C80,'Rule Updates'!$A:$A,0)),"Review")) | F80: 4227.43 | G80: 33502.77 | H80: 5 | I80: =IF(OR(D80="Uncategorised",E80=""),"Check","")
A81: Amex Oct-2024 | B81: 45572 | C81: HTL*ASCOTTORCHARDS 800-468-3578 | D81: =IFERROR(INDEX('Review Items'!$D:$D,MATCH(C81,'Review Items'!$B:$B,0)),IFERROR(INDEX('Rule Updates'!$B:$B,MATCH(C81,'Rule Updates'!$A:$A,0)),"Uncategorised")) | E81: =IFERROR(INDEX('Review Items'!$E:$E,MATCH(C81,'Review Items'!$B:$B,0)),IFERROR(INDEX('Rule Updates'!$C:$C,MATCH(C81,'Rule Updates'!$A:$A,0)),"Review")) | F81: 16347.65 | G81: -127016.34 | H81: 5 | I81: =IF(OR(D81="Uncategorised",E81=""),"Check","")
A82: Amex Oct-2024 | B82: 45572 | C82: HTL*ASCOTTORCHARDS 800-468-3578 | D82: =IFERROR(INDEX('Review Items'!$D:$D,MATCH(C82,'Review Items'!$B:$B,0)),IFERROR(INDEX('Rule Updates'!$B:$B,MATCH(C82,'Rule Updates'!$A:$A,0)),"Uncategorised")) | E82: =IFERROR(INDEX('Review Items'!$E:$E,MATCH(C82,'Review Items'!$B:$B,0)),IFERROR(INDEX('Rule Updates'!$C:$C,MATCH(C82,'Rule Updates'!$A:$A,0)),"Review")) | F82: 6428.01 | G82: 50929.46 | H82: 5 | I82: =IF(OR(D82="Uncategorised",E82=""),"Check","")
A83: Amex Oct-2024 | B83: 45572 | C83: PAYMENT RECEIVED THROUGH AUTOPAY | D83: =IFERROR(INDEX('Review Items'!$D:$D,MATCH(C83,'Review Items'!$B:$B,0)),IFERROR(INDEX('Rule Updates'!$B:$B,MATCH(C83,'Rule Updates'!$A:$A,0)),"Uncategorised")) | E83: =IFERROR(INDEX('Review Items'!$E:$E,MATCH(C83,'Review Items'!$B:$B,0)),IFERROR(INDEX('Rule Updates'!$C:$C,MATCH(C83,'Rule Updates'!$A:$A,0)),"Review")) | G83: -1598868.9 | H83: 1 | I83: =IF(OR(D83="Uncategorised",E83=""),"Check","")
A84: Amex Oct-2024 | B84: 45573 | C84: CARBONE CENTRAL | D84: =IFERROR(INDEX('Review Items'!$D:$D,MATCH(C84,'Review Items'!$B:$B,0)),IFERROR(INDEX('Rule Updates'!$B:$B,MATCH(C84,'Rule Updates'!$A:$A,0)),"Uncategorised")) | E84: =IFERROR(INDEX('Review Items'!$E:$E,MATCH(C84,'Review Items'!$B:$B,0)),IFERROR(INDEX('Rule Updates'!$C:$C,MATCH(C84,'Rule Updates'!$A:$A,0)),"Review")) | G84: 2150.4 | H84: 5 | I84: =IF(OR(D84="Uncategorised",E84=""),"Check","")
A85: Amex Oct-2024 | B85: 45573 | C85: IKEA CAUSEWAY BAY | D85: =IFERROR(INDEX('Review Items'!$D:$D,MATCH(C85,'Review Items'!$B:$B,0)),IFERROR(INDEX('Rule Updates'!$B:$B,MATCH(C85,'Rule Updates'!$A:$A,0)),"Uncategorised")) | E85: =IFERROR(INDEX('Review Items'!$E:$E,MATCH(C85,'Review Items'!$B:$B,0)),IFERROR(INDEX('Rule Updates'!$C:$C,MATCH(C85,'Rule Updates'!$A:$A,0)),"Review")) | G85: 1467.2 | H85: 2 | I85: =IF(OR(D85="Uncategorised",E85=""),"Check","")
A86: Amex Oct-2024 | B86: 45574 | C86: IKEA CAUSEWAY BAY | D86: =IFERROR(INDEX('Review Items'!$D:$D,MATCH(C86,'Review Items'!$B:$B,0)),IFERROR(INDEX('Rule Updates'!$B:$B,MATCH(C86,'Rule Updates'!$A:$A,0)),"Uncategorised")) | E86: =IFERROR(INDEX('Review Items'!$E:$E,MATCH(C86,'Review Items'!$B:$B,0)),IFERROR(INDEX('Rule Updates'!$C:$C,MATCH(C86,'Rule Updates'!$A:$A,0)),"Review")) | G86: 4223.2 | H86: 2 | I86: =IF(OR(D86="Uncategorised",E86=""),"Check","")
A87: Amex Oct-2024 | B87: 45575 | C87: AMAZON PRIME*TQ6OW4JL4 AMZN.CO.UK/PM | D87: =IFERROR(INDEX('Review Items'!$D:$D,MATCH(C87,'Review Items'!$B:$B,0)),IFERROR(INDEX('Rule Updates'!$B:$B,MATCH(C87,'Rule Updates'!$A:$A,0)),"Uncategorised")) | E87: =IFERROR(INDEX('Review Items'!$E:$E,MATCH(C87,'Review Items'!$B:$B,0)),IFERROR(INDEX('Rule Updates'!$C:$C,MATCH(C87,'Rule Updates'!$A:$A,0)),"Review")) | F87: 8.99 | G87: 93.41 | H87: 2 | I87: =IF(OR(D87="Uncategorised",E87=""),"Check","")
A88: Amex Oct-2024 | B88: 45575 | C88: GEORG JENSEN (IFC) CENTRAL | D88: =IFERROR(INDEX('Review Items'!$D:$D,MATCH(C88,'Review Items'!$B:$B,0)),IFERROR(INDEX('Rule Updates'!$B:$B,MATCH(C88,'Rule Updates'!$A:$A,0)),"Uncategorised")) | E88: =IFERROR(INDEX('Review Items'!$E:$E,MATCH(C88,'Review Items'!$B:$B,0)),IFERROR(INDEX('Rule Updates'!$C:$C,MATCH(C88,'Rule Updates'!$A:$A,0)),"Review")) | G88: 4500 | H88: 3 | I88: =IF(OR(D88="Uncategorised",E88=""),"Check","")
A89: Amex Oct-2024 | B89: 45575 | C89: PIERRE HERME PARIS CENTRAL | D89: =IFERROR(INDEX('Review Items'!$D:$D,MATCH(C89,'Review Items'!$B:$B,0)),IFERROR(INDEX('Rule Updates'!$B:$B,MATCH(C89,'Rule Updates'!$A:$A,0)),"Uncategorised")) | E89: =IFERROR(INDEX('Review Items'!$E:$E,MATCH(C89,'Review Items'!$B:$B,0)),IFERROR(INDEX('Rule Updates'!$C:$C,MATCH(C89,'Rule Updates'!$A:$A,0)),"Review")) | G89: 130 | H89: 2 | I89: =IF(OR(D89="Uncategorised",E89=""),"Check","")
A90: Amex Oct-2024 | B90: 45575 | C90: THE WING ON DEPARTMENT SHEUNG WAN | D90: =IFERROR(INDEX('Review Items'!$D:$D,MATCH(C90,'Review Items'!$B:$B,0)),IFERROR(INDEX('Rule Updates'!$B:$B,MATCH(C90,'Rule Updates'!$A:$A,0)),"Uncategorised")) | E90: =IFERROR(INDEX('Review Items'!$E:$E,MATCH(C90,'Review Items'!$B:$B,0)),IFERROR(INDEX('Rule Updates'!$C:$C,MATCH(C90,'Rule Updates'!$A:$A,0)),"Review")) | G90: 799 | H90: 2 | I90: =IF(OR(D90="Uncategorised",E90=""),"Check","")
A91: Amex Oct-2024 | B91: 45575 | C91: THE WING ON DEPARTMENT SHEUNG WAN | D91: =IFERROR(INDEX('Review Items'!$D:$D,MATCH(C91,'Review Items'!$B:$B,0)),IFERROR(INDEX('Rule Updates'!$B:$B,MATCH(C91,'Rule Updates'!$A:$A,0)),"Uncategorised")) | E91: =IFERROR(INDEX('Review Items'!$E:$E,MATCH(C91,'Review Items'!$B:$B,0)),IFERROR(INDEX('Rule Updates'!$C:$C,MATCH(C91,'Rule Updates'!$A:$A,0)),"Review")) | G91: 1708 | H91: 2 | I91: =IF(OR(D91="Uncategorised",E91=""),"Check","")
A92: Amex Oct-2024 | B92: 45575 | C92: WWW.HYUNDAI.COM SINGAPORE | D92: =IFERROR(INDEX('Review Items'!$D:$D,MATCH(C92,'Review Items'!$B:$B,0)),IFERROR(INDEX('Rule Updates'!$B:$B,MATCH(C92,'Rule Updates'!$A:$A,0)),"Uncategorised")) | E92: =IFERROR(INDEX('Review Items'!$E:$E,MATCH(C92,'Review Items'!$B:$B,0)),IFERROR(INDEX('Rule Updates'!$C:$C,MATCH(C92,'Rule Updates'!$A:$A,0)),"Review")) | F92: 779.35 | G92: 4742.32 | H92: 2 | I92: =IF(OR(D92="Uncategorised",E92=""),"Check","")
A93: Amex Oct-2024 | B93: 45576 | C93: Alice Pizza CTRL HK | D93: =IFERROR(INDEX('Review Items'!$D:$D,MATCH(C93,'Review Items'!$B:$B,0)),IFERROR(INDEX('Rule Updates'!$B:$B,MATCH(C93,'Rule Updates'!$A:$A,0)),"Uncategorised")) | E93: =IFERROR(INDEX('Review Items'!$E:$E,MATCH(C93,'Review Items'!$B:$B,0)),IFERROR(INDEX('Rule Updates'!$C:$C,MATCH(C93,'Rule Updates'!$A:$A,0)),"Review")) | G93: 261.1 | H93: 3 | I93: =IF(OR(D93="Uncategorised",E93=""),"Check","")
A94: Amex Oct-2024 | B94: 45577 | C94: APPLE.COM/BILL CUPERTINO | D94: =IFERROR(INDEX('Review Items'!$D:$D,MATCH(C94,'Review Items'!$B:$B,0)),IFERROR(INDEX('Rule Updates'!$B:$B,MATCH(C94,'Rule Updates'!$A:$A,0)),"Uncategorised")) | E94: =IFERROR(INDEX('Review Items'!$E:$E,MATCH(C94,'Review Items'!$B:$B,0)),IFERROR(INDEX('Rule Updates'!$C:$C,MATCH(C94,'Rule Updates'!$A:$A,0)),"Review")) | F94: 11.99 | G94: 95.05 | H94: 3 | I94: =IF(OR(D94="Uncategorised",E94=""),"Check","")
A95: Amex Oct-2024 | B95: 45577 | C95: GARMIN (EUROPE) LIMITED SOUTHAMPTON | D95: =IFERROR(INDEX('Review Items'!$D:$D,MATCH(C95,'Review Items'!$B:$B,0)),IFERROR(INDEX('Rule Updates'!$B:$B,MATCH(C95,'Rule Updates'!$A:$A,0)),"Uncategorised")) | E95: =IFERROR(INDEX('Review Items'!$E:$E,MATCH(C95,'Review Items'!$B:$B,0)),IFERROR(INDEX('Rule Updates'!$C:$C,MATCH(C95,'Rule Updates'!$A:$A,0)),"Review")) | F95: 9.99 | G95: 79.2 | H95: 3 | I95: =IF(OR(D95="Uncategorised",E95=""),"Check","")
A96: Amex Oct-2024 | B96: 45577 | C96: LUCALE SAI YING PUN | D96: =IFERROR(INDEX('Review Items'!$D:$D,MATCH(C96,'Review Items'!$B:$B,0)),IFERROR(INDEX('Rule Updates'!$B:$B,MATCH(C96,'Rule Updates'!$A:$A,0)),"Uncategorised")) | E96: =IFERROR(INDEX('Review Items'!$E:$E,MATCH(C96,'Review Items'!$B:$B,0)),IFERROR(INDEX('Rule Updates'!$C:$C,MATCH(C96,'Rule Updates'!$A:$A,0)),"Review")) | G96: 6384 | H96: 3 | I96: =IF(OR(D96="Uncategorised",E96=""),"Check","")
A97: Amex Oct-2024 | B97: 45578 | C97: AESOP IFC II CENTRAL | D97: =IFERROR(INDEX('Review Items'!$D:$D,MATCH(C97,'Review Items'!$B:$B,0)),IFERROR(INDEX('Rule Updates'!$B:$B,MATCH(C97,'Rule Updates'!$A:$A,0)),"Uncategorised")) | E97: =IFERROR(INDEX('Review Items'!$E:$E,MATCH(C97,'Review Items'!$B:$B,0)),IFERROR(INDEX('Rule Updates'!$C:$C,MATCH(C97,'Rule Updates'!$A:$A,0)),"Review")) | G97: 3710 | H97: 3 | I97: =IF(OR(D97="Uncategorised",E97=""),"Check","")
A98: Amex Oct-2024 | B98: 45578 | C98: APPLE.COM/BILL CUPERTINO | D98: =IFERROR(INDEX('Review Items'!$D:$D,MATCH(C98,'Review Items'!$B:$B,0)),IFERROR(INDEX('Rule Updates'!$B:$B,MATCH(C98,'Rule Updates'!$A:$A,0)),"Uncategorised")) | E98: =IFERROR(INDEX('Review Items'!$E:$E,MATCH(C98,'Review Items'!$B:$B,0)),IFERROR(INDEX('Rule Updates'!$C:$C,MATCH(C98,'Rule Updates'!$A:$A,0)),"Review")) | F98: 11.99 | G98: 95.05 | H98: 3 | I98: =IF(OR(D98="Uncategorised",E98=""),"Check","")
A99: Amex Oct-2024 | B99: 45578 | C99: APPLE.COM/BILL CUPERTINO | D99: =IFERROR(INDEX('Review Items'!$D:$D,MATCH(C99,'Review Items'!$B:$B,0)),IFERROR(INDEX('Rule Updates'!$B:$B,MATCH(C99,'Rule Updates'!$A:$A,0)),"Uncategorised")) | E99: =IFERROR(INDEX('Review Items'!$E:$E,MATCH(C99,'Review Items'!$B:$B,0)),IFERROR(INDEX('Rule Updates'!$C:$C,MATCH(C99,'Rule Updates'!$A:$A,0)),"Review")) | F99: 37.95 | G99: 300.85 | H99: 3 | I99: =IF(OR(D99="Uncategorised",E99=""),"Check","")
A100: Amex Oct-2024 | B100: 45578 | C100: CITY'SUPER CENTRAL | D100: =IFERROR(INDEX('Review Items'!$D:$D,MATCH(C100,'Review Items'!$B:$B,0)),IFERROR(INDEX('Rule Updates'!$B:$B,MATCH(C100,'Rule Updates'!$A:$A,0)),"Uncategorised")) | E100: =IFERROR(INDEX('Review Items'!$E:$E,MATCH(C100,'Review Items'!$B:$B,0)),IFERROR(INDEX('Rule Updates'!$C:$C,MATCH(C100,'Rule Updates'!$A:$A,0)),"Review")) | G100: 573.2 | H100: 3 | I100: =IF(OR(D100="Uncategorised",E100=""),"Check","")
A101: Amex Oct-2024 | B101: 45578 | C101: LANE CRAWFORD (IFC) CENTRAL | D101: =IFERROR(INDEX('Review Items'!$D:$D,MATCH(C101,'Review Items'!$B:$B,0)),IFERROR(INDEX('Rule Updates'!$B:$B,MATCH(C101,'Rule Updates'!$A:$A,0)),"Uncategorised")) | E101: =IFERROR(INDEX('Review Items'!$E:$E,MATCH(C101,'Review Items'!$B:$B,0)),IFERROR(INDEX('Rule Updates'!$C:$C,MATCH(C101,'Rule Updates'!$A:$A,0)),"Review")) | G101: 2490 | H101: 3 | I101: =IF(OR(D101="Uncategorised",E101=""),"Check","")
...

Sheet Rule Updates
A1: Rule Updates
A2: Use the dropdowns here to maintain merchant rules for future imports.
A4: Merchant | B4: Category | C4: Belongs To | D4: In Category? | E4: Suggested Match Text | F4: Action
A5: SILVERSEA LONDON | B5: Travel | C5: Family | D5: =IF(COUNTIF(Category!$A:$A,E5)>0,"Yes","No") | E5: =LEFT(A5,80) | F5: =IF(OR(B5="Uncategorised",C5="",C5="Review"),"Needs category/owner",IF(D5="Yes","Already in Category","Add to Category"))
A6: THE NET-A-PORTER GROUP HONG KONG | B6: Clothes & Shoes | C6: Su | D6: =IF(COUNTIF(Category!$A:$A,E6)>0,"Yes","No") | E6: =LEFT(A6,80) | F6: =IF(OR(B6="Uncategorised",C6="",C6="Review"),"Needs category/owner",IF(D6="Yes","Already in Category","Add to Category"))
A7: MYTHERESA APAC SERVICES ISLANDS | B7: Clothes & Shoes | C7: Su | D7: =IF(COUNTIF(Category!$A:$A,E7)>0,"Yes","No") | E7: =LEFT(A7,80) | F7: =IF(OR(B7="Uncategorised",C7="",C7="Review"),"Needs category/owner",IF(D7="Yes","Already in Category","Add to Category"))
A8: HTL*ASCOTTORCHARDS 800-468-3578 | B8: Hotel | C8: Family | D8: =IF(COUNTIF(Category!$A:$A,E8)>0,"Yes","No") | E8: =LEFT(A8,80) | F8: =IF(OR(B8="Uncategorised",C8="",C8="Review"),"Needs category/owner",IF(D8="Yes","Already in Category","Add to Category"))
A9: WHALE CLU BHK | B9: Dining out | C9: Family | D9: =IF(COUNTIF(Category!$A:$A,E9)>0,"Yes","No") | E9: =LEFT(A9,80) | F9: =IF(OR(B9="Uncategorised",C9="",C9="Review"),"Needs category/owner",IF(D9="Yes","Already in Category","Add to Category"))
A10: PONTI WINE CELLARS 0000 HONG KONG | B10: Wine | C10: Family | D10: =IF(COUNTIF(Category!$A:$A,E10)>0,"Yes","No") | E10: =LEFT(A10,80) | F10: =IF(OR(B10="Uncategorised",C10="",C10="Review"),"Needs category/owner",IF(D10="Yes","Already in Category","Add to Category"))
A11: LANE CRAWFORD (FURNITUR ADMIRALTY | B11: Housewares | C11: Family | D11: =IF(COUNTIF(Category!$A:$A,E11)>0,"Yes","No") | E11: =LEFT(A11,80) | F11: =IF(OR(B11="Uncategorised",C11="",C11="Review"),"Needs category/owner",IF(D11="Yes","Already in Category","Add to Category"))
A12: RAFFLES HOTEL SINGAPORE SINGAPORE | B12: Uncategorised | C12: Review | D12: =IF(COUNTIF(Category!$A:$A,E12)>0,"Yes","No") | E12: =LEFT(A12,80) | F12: =IF(OR(B12="Uncategorised",C12="",C12="Review"),"Needs category/owner",IF(D12="Yes","Already in Category","Add to Category"))
A13: AGORA IBIZA 367352630 SANT JOAN LAB | B13: Hotel | C13: Family | D13: =IF(COUNTIF(Category!$A:$A,E13)>0,"Yes","No") | E13: =LEFT(A13,80) | F13: =IF(OR(B13="Uncategorised",C13="",C13="Review"),"Needs category/owner",IF(D13="Yes","Already in Category","Add to Category"))
A14: FAR FETCH LONDON | B14: Clothes & Shoes | C14: Su | D14: =IF(COUNTIF(Category!$A:$A,E14)>0,"Yes","No") | E14: =LEFT(A14,80) | F14: =IF(OR(B14="Uncategorised",C14="",C14="Review"),"Needs category/owner",IF(D14="Yes","Already in Category","Add to Category"))
A15: BURGUNDY ETC CENTRAL | B15: Wine | C15: Family | D15: =IF(COUNTIF(Category!$A:$A,E15)>0,"Yes","No") | E15: =LEFT(A15,80) | F15: =IF(OR(B15="Uncategorised",C15="",C15="Review"),"Needs category/owner",IF(D15="Yes","Already in Category","Add to Category"))
A16: 3CPAYMENT*SIX SENSES IB GETARIA | B16: Hotel | C16: Family | D16: =IF(COUNTIF(Category!$A:$A,E16)>0,"Yes","No") | E16: =LEFT(A16,80) | F16: =IF(OR(B16="Uncategorised",C16="",C16="Review"),"Needs category/owner",IF(D16="Yes","Already in Category","Add to Category"))
... A692: TUMI ASIA LIMITED | B692: Uncategorised | C692: Review | D692: =IF(COUNTIF(Category!$A:$A,E692)>0,"Yes","No") | E692: =LEFT(A692,80) | F692: =IF(OR(B692="Uncategorised",C692="",C692="Review"),"Needs category/owner",IF(D692="Yes","Already in Category","Add to Category"))

Sheet Lists
A1: Categories | B1: Belongs To
A2: Airfare | B2: Family
A3: Art | B3: Payment
A4: Beauty | B4: Review
A5: Book & Kindle | B5: Su
A6: Charity
A7: Clinic
A8: Clothes & Shoes
A9: Dining out
A10: Electronics
A11: Entertainment
A12: Fees
A13: Fitness Equipment
A14: Flowers
A15: Food
A16: Glasses
A17: Groceries
... A36: beauty

Sheet Category
A1: Match Text | B1: Category | C1: Belongs To
A2: 10 Green Street | B2: Pharmacy | C2: Su
A3: 45R | B3: Clothes & Shoes | C3: Su
A4: 5 Hertford Street Limited | B4: Dining out | C4: Family
A5: Agolde | B5: Clothes & Shoes | C5: Su
A6: Amathus | B6: Dining out | C6: Family
A7: BA & SH | B7: Clothes & Shoes | C7: Su
A8: Bloomingdales | B8: Clothes & Shoes | C8: Su
A9: Blue Ojai | B9: Housewares | C9: Family
A10: Born in the sun | B10: Clothes & Shoes | C10: Su
A11: Caddis | B11: Glasses | C11: Su
A12: Cettire | B12: Clothes & Shoes | C12: Su
... A258: NEW CHITOSE | B258: Travel | C258: Family
